
{
  "name": "otiorhynchini",
  "children": [

    {
      "name": "Otiorhynchini Schönherr, 1826",
      "url": ""
    }
,
    {
      "name": "Otiorhynchus Germar, 1822",
      "url": ""
    }
,
    {
      "name": "Acunotus Reitter, 1912",
      "url": ""
    }
,
    {
      "name": "Arammichnus Gosis, 1882",
      "url": ""
    }
,
    {
      "name": "Aranihus Reitter, 1912",
      "url": ""
    }
,
    {
      "name": "Choilosanus Reitter, 1912",
      "url": ""
    }
,
    {
      "name": "Clypeotiorhynchus Yunakov & Arzanov, 2013",
      "url": ""
    }
,
    {
      "name": "Cryphiphorus Stierlin, 1883",
      "url": ""
    }
,
    {
      "name": "Dorymerus Seidlitz, 1890",
      "url": ""
    }
,
    {
      "name": "Duphanastus Reitter, 1914",
      "url": ""
    }
,
    {
      "name": "Elechranus Reitter, 1912",
      "url": ""
    }
,
    {
      "name": "Ergiferanus Reitter, 1912",
      "url": ""
    }
,
    {
      "name": "Italorrhynchus Magrini, 2019",
      "url": ""
    }
,
    {
      "name": "Lixorrhynchus Reitter, 1914",
      "url": ""
    }
,
    {
      "name": "Lolatismus Reitter, 1912",
      "url": ""
    }
,
    {
      "name": "Metopiorrhynchus Reitter, 1912",
      "url": ""
    }
,
    {
      "name": "Nehrodistus Reitter, 1912",
      "url": ""
    }
,
    {
      "name": "Nihus Reitter, 1912",
      "url": ""
    }
,
    {
      "name": "Otiolehus Reitter, 1914",
      "url": ""
    }
,
    {
      "name": "Otiorhynchus alpicola Boheman, 1842",
      "url": "https://inpn.mnhn.fr/espece/cd_nom/13064"
    }
,
    {
      "name": "Otiorhynchus aterrimus Boheman, 1843",
      "url": "https://inpn.mnhn.fr/espece/cd_nom/409500"
    }
,
    {
      "name": "Otiorhynchus binominatus Fauvel, 1885",
      "url": "https://inpn.mnhn.fr/espece/cd_nom/13068"
    }
,
    {
      "name": "Otiorhynchus brancsiki Stierlin",
      "url": "https://inpn.mnhn.fr/espece/cd_nom/13069"
    }
,
    {
      "name": "Otiorhynchus brancsiki Stierlin, 1883",
      "url": "https://inpn.mnhn.fr/espece/cd_nom/409504"
    }
,
    {
      "name": "Otiorhynchus calvus Fiori, 1899",
      "url": "https://inpn.mnhn.fr/espece/cd_nom/409505"
    }
,
    {
      "name": "Otiorhynchus gaudarti Stierlin, 1861",
      "url": "https://inpn.mnhn.fr/espece/cd_nom/13067"
    }
,
    {
      "name": "Otiorhynchus gautardi Stierlin, 1861",
      "url": "https://inpn.mnhn.fr/espece/cd_nom/409502"
    }
,
    {
      "name": "Otiorhynchus (Dorymerus) alpicola Boheman, 1843",
      "url": "https://inpn.mnhn.fr/espece/cd_nom/13065"
    }
,
    {
      "name": "Otiorhynchus javeti Stierlin, 1866",
      "url": "https://inpn.mnhn.fr/espece/cd_nom/409503"
    }
,
    {
      "name": "Otiorhynchus schwabi Stierlin, 1858",
      "url": "https://inpn.mnhn.fr/espece/cd_nom/409501"
    }
,
    {
      "name": "Otiorhynchus strigirostris Boheman, 1843",
      "url": "https://inpn.mnhn.fr/espece/cd_nom/242576"
    }
,
    {
      "name": "Otiorhynchus anthracinus (Scopoli, 1763)",
      "url": "https://inpn.mnhn.fr/espece/cd_nom/13091"
    }
,
    {
      "name": "Curculio anthracinus Scopoli, 1763",
      "url": "https://inpn.mnhn.fr/espece/cd_nom/803578"
    }
,
    {
      "name": "Curculio rugulipennis Costa, 1858",
      "url": "https://inpn.mnhn.fr/espece/cd_nom/409523"
    }
,
    {
      "name": "Otiorhynchus calabrus Stierlin, 1880",
      "url": "https://inpn.mnhn.fr/espece/cd_nom/409525"
    }
,
    {
      "name": "Otiorhynchus coenobita Marseul, 1876",
      "url": "https://inpn.mnhn.fr/espece/cd_nom/409524"
    }
,
    {
      "name": "Otiorhynchus cratoscelis Hustache",
      "url": "https://inpn.mnhn.fr/espece/cd_nom/13095"
    }
,
    {
      "name": "Otiorhynchus cratoscelis Reitter, 1812",
      "url": "https://inpn.mnhn.fr/espece/cd_nom/409526"
    }
,
    {
      "name": "Otiorhynchus deleticollis Reitter, 1914",
      "url": "https://inpn.mnhn.fr/espece/cd_nom/409527"
    }
,
    {
      "name": "Otiorhynchus helveticus Boheman",
      "url": "https://inpn.mnhn.fr/espece/cd_nom/13093"
    }
,
    {
      "name": "Otiorhynchus helvetius Boheman, 1843",
      "url": "https://inpn.mnhn.fr/espece/cd_nom/409522"
    }
,
    {
      "name": "Otiorhynchus (Arammichnus) anthracinus ",
      "url": "https://inpn.mnhn.fr/espece/cd_nom/13092"
    }
,
    {
      "name": "Otiorhynchus lazarevici Csiki, 1904",
      "url": "https://inpn.mnhn.fr/espece/cd_nom/409528"
    }
,
    {
      "name": "Otiorhynchus arcticus (O. Fabricius, 1780)",
      "url": "https://inpn.mnhn.fr/espece/cd_nom/12415"
    }
,
    {
      "name": "Curculio arcticus O. Fabricius, 1780",
      "url": "https://inpn.mnhn.fr/espece/cd_nom/803583"
    }
,
    {
      "name": "Otiorhynchus arcticus arcticus (O. Fabricius, 1780)",
      "url": "https://inpn.mnhn.fr/espece/cd_nom/252857"
    }
,
    {
      "name": "Curculio alpinus Richter, 1820",
      "url": "https://inpn.mnhn.fr/espece/cd_nom/409419"
    }
,
    {
      "name": "Otiorhynchus blandus Gyllenhal, 1834",
      "url": "https://inpn.mnhn.fr/espece/cd_nom/409420"
    }
,
    {
      "name": "Otiorhynchus laevigatus Gyllenhal, 1834",
      "url": "https://inpn.mnhn.fr/espece/cd_nom/409421"
    }
,
    {
      "name": "Otiorhynchus arcticus jugicola Stierlin, 1861",
      "url": "https://inpn.mnhn.fr/espece/cd_nom/326626"
    }
,
    {
      "name": "Otiorhynchus arcticus monticola Germar, 1823",
      "url": "https://inpn.mnhn.fr/espece/cd_nom/252858"
    }
,
    {
      "name": "Otiorhynchus monticola Germar, 1823",
      "url": "https://inpn.mnhn.fr/espece/cd_nom/934694"
    }
,
    {
      "name": "Otiorhynchus armadillo (Rossi, 1792)",
      "url": "https://inpn.mnhn.fr/espece/cd_nom/11800"
    }
,
    {
      "name": "Brachyrrhinus apenninus Fauvel, 1885",
      "url": "https://inpn.mnhn.fr/espece/cd_nom/728030"
    }
,
    {
      "name": "Brachyrrhinus latissimus Fauvel, 1885",
      "url": "https://inpn.mnhn.fr/espece/cd_nom/728031"
    }
,
    {
      "name": "Brachyrrhinus obsitus Fauvel, 1885",
      "url": "https://inpn.mnhn.fr/espece/cd_nom/728032"
    }
,
    {
      "name": "Brachyrrhinus scabripennis Fauvel, 1885",
      "url": "https://inpn.mnhn.fr/espece/cd_nom/728033"
    }
,
    {
      "name": "Curculio armadillo Rossi, 1792",
      "url": "https://inpn.mnhn.fr/espece/cd_nom/728026"
    }
,
    {
      "name": "Curculio nigrita Rossi, 1790",
      "url": "https://inpn.mnhn.fr/espece/cd_nom/409338"
    }
,
    {
      "name": "Curculio orbicularis Olivier, 1807",
      "url": "https://inpn.mnhn.fr/espece/cd_nom/728027"
    }
,
    {
      "name": "Curculio sulphurifer Herbst, 1797",
      "url": "https://inpn.mnhn.fr/espece/cd_nom/409339"
    }
,
    {
      "name": "Otiorhynchus amardillo Guillebeau, 1892",
      "url": "https://inpn.mnhn.fr/espece/cd_nom/409346"
    }
,
    {
      "name": "Otiorhynchus collinus Gredler, 1863",
      "url": "https://inpn.mnhn.fr/espece/cd_nom/409345"
    }
,
    {
      "name": "Otiorhynchus halbherri Stierlin, 1890",
      "url": "https://inpn.mnhn.fr/espece/cd_nom/409347"
    }
,
    {
      "name": "Otiorhynchus (Otiorhynchus) halbherri Stierlin, 1890",
      "url": "https://inpn.mnhn.fr/espece/cd_nom/728034"
    }
,
    {
      "name": "Otiorhynchus (Otiorhynchus) latissimus Stierlin, 1861",
      "url": "https://inpn.mnhn.fr/espece/cd_nom/728029"
    }
,
    {
      "name": "Otiorhynchus latipennis Stierlin, 1861",
      "url": "https://inpn.mnhn.fr/espece/cd_nom/409343"
    }
,
    {
      "name": "Otiorhynchus latissimus Stierlin, 1861",
      "url": "https://inpn.mnhn.fr/espece/cd_nom/409342"
    }
,
    {
      "name": "Otiorhynchus obsitus Gyllenhal, 1834",
      "url": "https://inpn.mnhn.fr/espece/cd_nom/409341"
    }
,
    {
      "name": "Otiorhynchus rhaeticus Stierlin, 1862",
      "url": "https://inpn.mnhn.fr/espece/cd_nom/409344"
    }
,
    {
      "name": "Otiorhynchus scabripennis Gyllenhal, 1834",
      "url": "https://inpn.mnhn.fr/espece/cd_nom/409340"
    }
,
    {
      "name": "Otiorhynchus ventricola Weise, 1894",
      "url": "https://inpn.mnhn.fr/espece/cd_nom/11802"
    }
,
    {
      "name": "Otiorhynchus armatus Boheman, 1842",
      "url": "https://inpn.mnhn.fr/espece/cd_nom/326920"
    }
,
    {
      "name": "Otiorhynchus armatus armatus Boheman, 1842",
      "url": "https://inpn.mnhn.fr/espece/cd_nom/795762"
    }
,
    {
      "name": "Otiorhynchus atroapterus (De Geer, 1775)",
      "url": "https://inpn.mnhn.fr/espece/cd_nom/13102"
    }
,
    {
      "name": "Curculio atroapterus De Geer, 1775",
      "url": "https://inpn.mnhn.fr/espece/cd_nom/803590"
    }
,
    {
      "name": "Curculio rotundatus Gmelin, 1790",
      "url": "https://inpn.mnhn.fr/espece/cd_nom/409434"
    }
,
    {
      "name": "Otiorhynchus arenosus Stierlin, 1861",
      "url": "https://inpn.mnhn.fr/espece/cd_nom/326711"
    }
,
    {
      "name": "Otiorhynchus bergamascus Stierlin, 1894",
      "url": "https://inpn.mnhn.fr/espece/cd_nom/431920"
    }
,
    {
      "name": "Otiorhynchus (Arammichnus) atroapterus ",
      "url": "https://inpn.mnhn.fr/espece/cd_nom/13103"
    }
,
    {
      "name": "Otiorhynchus perezi Stierlin, 1862",
      "url": "https://inpn.mnhn.fr/espece/cd_nom/409435"
    }
,
    {
      "name": "Otiorhynchus valtellinus J. Daniel & K. Daniel, 1891",
      "url": "https://inpn.mnhn.fr/espece/cd_nom/432102"
    }
,
    {
      "name": "Otiorhynchus auricomus Germar, 1823",
      "url": "https://inpn.mnhn.fr/espece/cd_nom/13039"
    }
,
    {
      "name": "Otiorhynchus (Dorymerus) auricomus Germar, 1823",
      "url": "https://inpn.mnhn.fr/espece/cd_nom/13040"
    }
,
    {
      "name": "Otiorhynchus nivalis Stierlin",
      "url": "https://inpn.mnhn.fr/espece/cd_nom/13041"
    }
,
    {
      "name": "Otiorhynchus nivalis Stierlin, 1862",
      "url": "https://inpn.mnhn.fr/espece/cd_nom/409492"
    }
,
    {
      "name": "Otiorhynchus aurifer Boheman, 1842",
      "url": "https://inpn.mnhn.fr/espece/cd_nom/242553"
    }
,
    {
      "name": "Otiorhynchus lefebvrei Gyllenhal, 1843",
      "url": "https://inpn.mnhn.fr/espece/cd_nom/409348"
    }
,
    {
      "name": "Otiorhynchus morulus Boheman, 1843",
      "url": "https://inpn.mnhn.fr/espece/cd_nom/409349"
    }
,
    {
      "name": "Otiorhynchus auropunctatus Gyllenhal, 1834",
      "url": "https://inpn.mnhn.fr/espece/cd_nom/242554"
    }
,
    {
      "name": "Otiorhynchus coryli Chevrolati, 1863",
      "url": "https://inpn.mnhn.fr/espece/cd_nom/409355"
    }
,
    {
      "name": "Otiorhynchus fossor Boheman, 1843",
      "url": "https://inpn.mnhn.fr/espece/cd_nom/409350"
    }
,
    {
      "name": "Otiorhynchus lafertei Stierlin, 1861",
      "url": "https://inpn.mnhn.fr/espece/cd_nom/409353"
    }
,
    {
      "name": "Otiorhynchus obsimulatus Dufour, 1843",
      "url": "https://inpn.mnhn.fr/espece/cd_nom/409352"
    }
,
    {
      "name": "Otiorhynchus rufipes Boheman, 1843",
      "url": "https://inpn.mnhn.fr/espece/cd_nom/409351"
    }
,
    {
      "name": "Otiorhynchus sicardi Hoffmann, 1950",
      "url": "https://inpn.mnhn.fr/espece/cd_nom/409356"
    }
,
    {
      "name": "Otiorhynchus tumefactus Stierlin, 1861",
      "url": "https://inpn.mnhn.fr/espece/cd_nom/409354"
    }
,
    {
      "name": "Otiorhynchus axatensis Hoffmann, 1930",
      "url": "https://inpn.mnhn.fr/espece/cd_nom/13020"
    }
,
    {
      "name": "Otiorhynchus (Dorymerus) axatensis ",
      "url": "https://inpn.mnhn.fr/espece/cd_nom/13021"
    }
,
    {
      "name": "Otiorhynchus baraudi Tempère, 1977",
      "url": "https://inpn.mnhn.fr/espece/cd_nom/12418"
    }
,
    {
      "name": "Otiorhynchus bigoti Tempère & Ponel, 1983",
      "url": "https://inpn.mnhn.fr/espece/cd_nom/11817"
    }
,
    {
      "name": "Otiorhynchus brunneus Gyllenhal, 1834",
      "url": "https://inpn.mnhn.fr/espece/cd_nom/793155"
    }
,
    {
      "name": "Otiorhynchus brunneus Krynicki, 1834",
      "url": "https://inpn.mnhn.fr/espece/cd_nom/242579"
    }
,
    {
      "name": "Otiorhynchus crispus Boheman, 1843",
      "url": "https://inpn.mnhn.fr/espece/cd_nom/409573"
    }
,
    {
      "name": "Otiorhynchus fulvicomus Lona, 1922",
      "url": "https://inpn.mnhn.fr/espece/cd_nom/409575"
    }
,
    {
      "name": "Otiorhynchus jacqueti Stierlin, 1901",
      "url": "https://inpn.mnhn.fr/espece/cd_nom/409574"
    }
,
    {
      "name": "Otiorhynchus monspeliensis Hoffmann, 1962",
      "url": "https://inpn.mnhn.fr/espece/cd_nom/798423"
    }
,
    {
      "name": "Otiorhynchus pubifer Boheman, 1843",
      "url": "https://inpn.mnhn.fr/espece/cd_nom/409572"
    }
,
    {
      "name": "Otiorhynchus caesipes Mulsant & Rey, 1859",
      "url": "https://inpn.mnhn.fr/espece/cd_nom/242561"
    }
,
    {
      "name": "Otiorhynchus caesipus Grenier, 1863",
      "url": "https://inpn.mnhn.fr/espece/cd_nom/409422"
    }
,
    {
      "name": "Otiorhynchus cancellatus Boheman, 1842",
      "url": "https://inpn.mnhn.fr/espece/cd_nom/13033"
    }
,
    {
      "name": "Otiorhynchus clairi Stierlin, 1880",
      "url": "https://inpn.mnhn.fr/espece/cd_nom/798425"
    }
,
    {
      "name": "Otiorhynchus (Dorymerus) cancellatus ",
      "url": "https://inpn.mnhn.fr/espece/cd_nom/13034"
    }
,
    {
      "name": "Otiorhynchus carinatopunctatus (Retzius, 1783)",
      "url": "https://inpn.mnhn.fr/espece/cd_nom/794926"
    }
,
    {
      "name": "Curculio carinatopunctatus Retzius, 1783",
      "url": "https://inpn.mnhn.fr/espece/cd_nom/803577"
    }
,
    {
      "name": "Otiorhynchus chobauti Hustache, 1920",
      "url": "https://inpn.mnhn.fr/espece/cd_nom/11819"
    }
,
    {
      "name": "Otiorhynchus falcozi Hoffmann, 1950",
      "url": "https://inpn.mnhn.fr/espece/cd_nom/409423"
    }
,
    {
      "name": "Otiorrhynchus chobauti Hustache, 1920",
      "url": "https://inpn.mnhn.fr/espece/cd_nom/978978"
    }
,
    {
      "name": "Otiorhynchus chrysocomus Germar, 1823",
      "url": "https://inpn.mnhn.fr/espece/cd_nom/242578"
    }
,
    {
      "name": "Otiorhynchus laevigaticollis Gredler, 1857",
      "url": "https://inpn.mnhn.fr/espece/cd_nom/409569"
    }
,
    {
      "name": "Otiorhynchus ostrovi Angelov, 1961",
      "url": "https://inpn.mnhn.fr/espece/cd_nom/409571"
    }
,
    {
      "name": "Otiorhynchus viridicomus Stierlin, 1891",
      "url": "https://inpn.mnhn.fr/espece/cd_nom/409570"
    }
,
    {
      "name": "Otiorhynchus claudiae Perez, Cantot, Rouault & Komeza, 2020",
      "url": "https://inpn.mnhn.fr/espece/cd_nom/970737"
    }
,
    {
      "name": "Otiorhynchus coachei Delaunay, 2005",
      "url": "https://inpn.mnhn.fr/espece/cd_nom/443343"
    }
,
    {
      "name": "Otiorhynchus coecus Germar, 1823",
      "url": "https://inpn.mnhn.fr/espece/cd_nom/242555"
    }
,
    {
      "name": "Otiorhynchus coecus coecus Germar, 1823",
      "url": "https://inpn.mnhn.fr/espece/cd_nom/252850"
    }
,
    {
      "name": "Curculio ater Herbst, 1795",
      "url": "https://inpn.mnhn.fr/espece/cd_nom/409358"
    }
,
    {
      "name": "Curculio multipunctatus Olivier, 1807",
      "url": "https://inpn.mnhn.fr/espece/cd_nom/409360"
    }
,
    {
      "name": "Curculio niger Fabricius, 1775",
      "url": "https://inpn.mnhn.fr/espece/cd_nom/409357"
    }
,
    {
      "name": "Curculio perlatus Richter, 1820",
      "url": "https://inpn.mnhn.fr/espece/cd_nom/409359"
    }
,
    {
      "name": "Otiorhynchus angustatus Stierlin, 1861",
      "url": "https://inpn.mnhn.fr/espece/cd_nom/409366"
    }
,
    {
      "name": "Otiorhynchus haematopus Boheman, 1843",
      "url": "https://inpn.mnhn.fr/espece/cd_nom/409364"
    }
,
    {
      "name": "Otiorhynchus montanus Boheman, 1843",
      "url": "https://inpn.mnhn.fr/espece/cd_nom/409363"
    }
,
    {
      "name": "Otiorhynchus niger (Fabricius, 1775)",
      "url": "https://inpn.mnhn.fr/espece/cd_nom/853381"
    }
,
    {
      "name": "Otiorhynchus rugipennis Boheman, 1843",
      "url": "https://inpn.mnhn.fr/espece/cd_nom/409365"
    }
,
    {
      "name": "Otiorhynchus scrobiculatus Gyllenhal, 1834",
      "url": "https://inpn.mnhn.fr/espece/cd_nom/409362"
    }
,
    {
      "name": "Otiorhynchus villosopunctatus Gyllenhal, 1834",
      "url": "https://inpn.mnhn.fr/espece/cd_nom/409361"
    }
,
    {
      "name": "Otiorhynchus coecus mequignoni Hoffmann, 1938",
      "url": "https://inpn.mnhn.fr/espece/cd_nom/252851"
    }
,
    {
      "name": "Otiorhynchus corruptor (Host, 1789)",
      "url": "https://inpn.mnhn.fr/espece/cd_nom/326922"
    }
,
    {
      "name": "Curculio corruptor Host, 1789",
      "url": "https://inpn.mnhn.fr/espece/cd_nom/803576"
    }
,
    {
      "name": "Otiorhynchus corruptor corruptor (Host, 1789)",
      "url": "https://inpn.mnhn.fr/espece/cd_nom/326923"
    }
,
    {
      "name": "Otiorhynchus corsicus Fairmaire, 1859",
      "url": "https://inpn.mnhn.fr/espece/cd_nom/12422"
    }
,
    {
      "name": "Otiorhynchus balachowskyi Hoffmann, 1934",
      "url": "https://inpn.mnhn.fr/espece/cd_nom/798430"
    }
,
    {
      "name": "Otiorhynchus corticalis Lucas, 1847",
      "url": "https://inpn.mnhn.fr/espece/cd_nom/326556"
    }
,
    {
      "name": "Otiorhynchus crataegi Germar, 1823",
      "url": "https://inpn.mnhn.fr/espece/cd_nom/242577"
    }
,
    {
      "name": "Otiorhynchus cratagei Germar, 1823",
      "url": "https://inpn.mnhn.fr/espece/cd_nom/13077"
    }
,
    {
      "name": "Otiorhynchus (Tournieria) cratagei Germar, 1823",
      "url": "https://inpn.mnhn.fr/espece/cd_nom/13078"
    }
,
    {
      "name": "Otiorhynchus cribricollis Gyllenhal, 1834",
      "url": "https://inpn.mnhn.fr/espece/cd_nom/13104"
    }
,
    {
      "name": "Otiorhynchus (Arammichnus) cribricollis ",
      "url": "https://inpn.mnhn.fr/espece/cd_nom/13105"
    }
,
    {
      "name": "Otiorhynchus kairuanus Reitter, 1912",
      "url": "https://inpn.mnhn.fr/espece/cd_nom/431994"
    }
,
    {
      "name": "Otiorhynchus terrestris Marseul, 1872",
      "url": "https://inpn.mnhn.fr/espece/cd_nom/13106"
    }
,
    {
      "name": "Otiorhynchus cupreosparsus Fairmaire, 1859",
      "url": "https://inpn.mnhn.fr/espece/cd_nom/12409"
    }
,
    {
      "name": "Otiorhynchus crinitarsis Stierlin, 1861",
      "url": "https://inpn.mnhn.fr/espece/cd_nom/409424"
    }
,
    {
      "name": "Otiorhynchus cupreoparsus Stein, 1868",
      "url": "https://inpn.mnhn.fr/espece/cd_nom/409425"
    }
,
    {
      "name": "Otiorhynchus cuprosparsus Fairmaire, 1859",
      "url": "https://inpn.mnhn.fr/espece/cd_nom/242562"
    }
,
    {
      "name": "Otiorhynchus delicatulus Stierlin, 1872",
      "url": "https://inpn.mnhn.fr/espece/cd_nom/793156"
    }
,
    {
      "name": "Otiorhynchus delicatulus Marseul, 1872",
      "url": "https://inpn.mnhn.fr/espece/cd_nom/13008"
    }
,
    {
      "name": "Otiorhynchus (Dorymerus) delicatulus ",
      "url": "https://inpn.mnhn.fr/espece/cd_nom/13009"
    }
,
    {
      "name": "Otiorhynchus rivierae Stierlin, 1883",
      "url": "https://inpn.mnhn.fr/espece/cd_nom/409472"
    }
,
    {
      "name": "Otiorhynchus densatus Boheman, 1842",
      "url": "https://inpn.mnhn.fr/espece/cd_nom/12434"
    }
,
    {
      "name": "Otiorhynchus grisescens Mulsant, 1859",
      "url": "https://inpn.mnhn.fr/espece/cd_nom/242566"
    }
,
    {
      "name": "Otiorhynchus desertus Rosenhauer, 1847",
      "url": "https://inpn.mnhn.fr/espece/cd_nom/13083"
    }
,
    {
      "name": "Otiorhynchus abietinus Apfelbeck, 1898",
      "url": "https://inpn.mnhn.fr/espece/cd_nom/409561"
    }
,
    {
      "name": "Otiorhynchus (Tournieria) desertus ",
      "url": "https://inpn.mnhn.fr/espece/cd_nom/13084"
    }
,
    {
      "name": "Otiorhynchus muscorum Brisout, 1863",
      "url": "https://inpn.mnhn.fr/espece/cd_nom/409560"
    }
,
    {
      "name": "Otiorhynchus pellucidus Sahlberg, 1900",
      "url": "https://inpn.mnhn.fr/espece/cd_nom/409562"
    }
,
    {
      "name": "Otiorhynchus difficilis Stierlin, 1858",
      "url": "https://inpn.mnhn.fr/espece/cd_nom/13030"
    }
,
    {
      "name": "Otiorhynchus (Dorymerus) difficilis ",
      "url": "https://inpn.mnhn.fr/espece/cd_nom/13031"
    }
,
    {
      "name": "Otiorhynchus simplonicus Stierlin, 1886",
      "url": "https://inpn.mnhn.fr/espece/cd_nom/409473"
    }
,
    {
      "name": "Otiorhynchus fagniezi Ruter, 1945",
      "url": "https://inpn.mnhn.fr/espece/cd_nom/13057"
    }
,
    {
      "name": "Otiorhynchus (Dorymerus) fagniezi Ruter, 1945",
      "url": "https://inpn.mnhn.fr/espece/cd_nom/13058"
    }
,
    {
      "name": "Otiorhynchus frigidus Mulsant & Rey, 1859",
      "url": "https://inpn.mnhn.fr/espece/cd_nom/326800"
    }
,
    {
      "name": "Otiorhynchus plicicollis Reitter, 1914",
      "url": "https://inpn.mnhn.fr/espece/cd_nom/432045"
    }
,
    {
      "name": "Otiorhynchus fullo (Schrank, 1781)",
      "url": "https://inpn.mnhn.fr/espece/cd_nom/13074"
    }
,
    {
      "name": "Curculio carinatus Paykull, 1792",
      "url": "https://inpn.mnhn.fr/espece/cd_nom/409548"
    }
,
    {
      "name": "Curculio fullo Schrank, 1781",
      "url": "https://inpn.mnhn.fr/espece/cd_nom/803586"
    }
,
    {
      "name": "Curculio zebra Fabricius, 1792",
      "url": "https://inpn.mnhn.fr/espece/cd_nom/409549"
    }
,
    {
      "name": "Otiorhynchus (Tournieria) fullo (Schrank, 1781)",
      "url": "https://inpn.mnhn.fr/espece/cd_nom/13075"
    }
,
    {
      "name": "Otiorhynchus subsetulosus Stierlin, 1891",
      "url": "https://inpn.mnhn.fr/espece/cd_nom/409550"
    }
,
    {
      "name": "Otiorhynchus fulvipes Gyllenhal, 1834",
      "url": "https://inpn.mnhn.fr/espece/cd_nom/12423"
    }
,
    {
      "name": "Otiorhynchus gemmatus (Scopoli, 1763)",
      "url": "https://inpn.mnhn.fr/espece/cd_nom/13042"
    }
,
    {
      "name": "Curculio gemmatus Scopoli, 1763",
      "url": "https://inpn.mnhn.fr/espece/cd_nom/803588"
    }
,
    {
      "name": "Curculio religiosus Schrank, 1871",
      "url": "https://inpn.mnhn.fr/espece/cd_nom/409518"
    }
,
    {
      "name": "Curculio squamiger Olivier, 1807",
      "url": "https://inpn.mnhn.fr/espece/cd_nom/409519"
    }
,
    {
      "name": "Otiorhynchus chlorophanus Germar, 1824",
      "url": "https://inpn.mnhn.fr/espece/cd_nom/409520"
    }
,
    {
      "name": "Otiorhynchus germari Stierlin, 1877",
      "url": "https://inpn.mnhn.fr/espece/cd_nom/409521"
    }
,
    {
      "name": "Otiorhynchus (Dorymerus) gemmatus ",
      "url": "https://inpn.mnhn.fr/espece/cd_nom/13043"
    }
,
    {
      "name": "Otiorhynchus ghilianii Fairmaire, 1857",
      "url": "https://inpn.mnhn.fr/espece/cd_nom/242556"
    }
,
    {
      "name": "Otiorhynchus ghiliani Fairmaire, 1857",
      "url": "https://inpn.mnhn.fr/espece/cd_nom/11803"
    }
,
    {
      "name": "Otiorhynchus globus Boheman, 1843",
      "url": "https://inpn.mnhn.fr/espece/cd_nom/1002883"
    }
,
    {
      "name": "Otiorhynchus gracilis Gyllenhal, 1834",
      "url": "https://inpn.mnhn.fr/espece/cd_nom/13036"
    }
,
    {
      "name": "Otiorhynchus (Dorymerus) gracilis ",
      "url": "https://inpn.mnhn.fr/espece/cd_nom/13037"
    }
,
    {
      "name": "Otiorhynchus provincialis Stierlin",
      "url": "https://inpn.mnhn.fr/espece/cd_nom/13038"
    }
,
    {
      "name": "Otiorhynchus provincialis Stierlin, 1861",
      "url": "https://inpn.mnhn.fr/espece/cd_nom/409489"
    }
,
    {
      "name": "Otiorhynchus grenieri (Allard, 1869)",
      "url": "https://inpn.mnhn.fr/espece/cd_nom/242573"
    }
,
    {
      "name": "Otiorhynchus pavesii Magrini, Magnano & Abazzi, 2007",
      "url": "https://inpn.mnhn.fr/espece/cd_nom/794925"
    }
,
    {
      "name": "Troglorhynchus grenieri Allard, 1869",
      "url": "https://inpn.mnhn.fr/espece/cd_nom/13125"
    }
,
    {
      "name": "Otiorhynchus grouvellei Stierlin, 1883",
      "url": "https://inpn.mnhn.fr/espece/cd_nom/242557"
    }
,
    {
      "name": "Otiorhynchus guttula Fairmaire, 1859",
      "url": "https://inpn.mnhn.fr/espece/cd_nom/12445"
    }
,
    {
      "name": "Otiorhynchus guttula guttula Fairmaire, 1859",
      "url": "https://inpn.mnhn.fr/espece/cd_nom/795760"
    }
,
    {
      "name": "Otiorhynchus hungaricus Germar, 1823",
      "url": "https://inpn.mnhn.fr/espece/cd_nom/12442"
    }
,
    {
      "name": "Otiorhynchus hungaricus hospitellensis Hustache, 1923",
      "url": "https://inpn.mnhn.fr/espece/cd_nom/12443"
    }
,
    {
      "name": "Otiorhynchus hospitellensis Hustache, 1923",
      "url": "https://inpn.mnhn.fr/espece/cd_nom/242558"
    }
,
    {
      "name": "Otiorhynchus hypocrita Rosenhauer, 1847",
      "url": "https://inpn.mnhn.fr/espece/cd_nom/12444"
    }
,
    {
      "name": "Otiorhynchus impressiventris Fairmaire, 1859",
      "url": "https://inpn.mnhn.fr/espece/cd_nom/13022"
    }
,
    {
      "name": "Otiorhynchus (Dorymerus) impressiventris ",
      "url": "https://inpn.mnhn.fr/espece/cd_nom/13023"
    }
,
    {
      "name": "Otiorhynchus indefinitus Reitter, 1912",
      "url": "https://inpn.mnhn.fr/espece/cd_nom/242581"
    }
,
    {
      "name": "Otiorhynchus dieckmanni Magnano, 1979",
      "url": "https://inpn.mnhn.fr/espece/cd_nom/242580"
    }
,
    {
      "name": "Otiorhynchus indefinitus indefinitus Reitter, 1912",
      "url": "https://inpn.mnhn.fr/espece/cd_nom/252874"
    }
,
    {
      "name": "Otiorhynchus insubricus (Comolli, 1837)",
      "url": "https://inpn.mnhn.fr/espece/cd_nom/794927"
    }
,
    {
      "name": "Loborynchus insubricus Comolli, 1837",
      "url": "https://inpn.mnhn.fr/espece/cd_nom/803579"
    }
,
    {
      "name": "Otiorhynchus insubricus J. Cristoforus & G. J. Cristoforus, 1833",
      "url": "https://inpn.mnhn.fr/espece/cd_nom/11809"
    }
,
    {
      "name": "Otiorhynchus lanuginosus Boheman, 1843",
      "url": "https://inpn.mnhn.fr/espece/cd_nom/11808"
    }
,
    {
      "name": "Otiorhynchus neglectus Stierlin, 1858",
      "url": "https://inpn.mnhn.fr/espece/cd_nom/409374"
    }
,
    {
      "name": "Otiorhynchus intrusus Reiche, 1862",
      "url": "https://inpn.mnhn.fr/espece/cd_nom/12455"
    }
,
    {
      "name": "Otiorhynchus (Dorymerus) intrusus ",
      "url": "https://inpn.mnhn.fr/espece/cd_nom/12456"
    }
,
    {
      "name": "Otiorhynchus koziorowiczi Stierlin, 1883",
      "url": "https://inpn.mnhn.fr/espece/cd_nom/409474"
    }
,
    {
      "name": "Otiorhynchus johannis Stierlin, 1881",
      "url": "https://inpn.mnhn.fr/espece/cd_nom/242563"
    }
,
    {
      "name": "Otiorhynchus juvencus Gyllenhal, 1834",
      "url": "https://inpn.mnhn.fr/espece/cd_nom/13110"
    }
,
    {
      "name": "Otiorhynchus (Arammichnus) juvencus ",
      "url": "https://inpn.mnhn.fr/espece/cd_nom/13111"
    }
,
    {
      "name": "Otiorhynchus juvencus juvencus Gyllenhal, 1834",
      "url": "https://inpn.mnhn.fr/espece/cd_nom/252875"
    }
,
    {
      "name": "Otiorhynchus levasseuri Roudier, 1961",
      "url": "https://inpn.mnhn.fr/espece/cd_nom/12441"
    }
,
    {
      "name": "Otiorhynchus ligneus (Olivier, 1807)",
      "url": "https://inpn.mnhn.fr/espece/cd_nom/12447"
    }
,
    {
      "name": "Curculio ligneus Olivier, 1807",
      "url": "https://inpn.mnhn.fr/espece/cd_nom/803570"
    }
,
    {
      "name": "Otiorhynchus ligneus ligneus (Olivier, 1807)",
      "url": "https://inpn.mnhn.fr/espece/cd_nom/252867"
    }
,
    {
      "name": "Otiorhynchus frisius Schneider, 1896",
      "url": "https://inpn.mnhn.fr/espece/cd_nom/409471"
    }
,
    {
      "name": "Otiorhynchus gallicanus Gyllenhal, 1834",
      "url": "https://inpn.mnhn.fr/espece/cd_nom/409469"
    }
,
    {
      "name": "Otiorhynchus hispidulus Stierlin, 1861",
      "url": "https://inpn.mnhn.fr/espece/cd_nom/409470"
    }
,
    {
      "name": "Otiorhynchus scabridus Stephens, 1831",
      "url": "https://inpn.mnhn.fr/espece/cd_nom/409468"
    }
,
    {
      "name": "Otiorhynchus setosus Stierlin, 1858",
      "url": "https://inpn.mnhn.fr/espece/cd_nom/798422"
    }
,
    {
      "name": "Otiorhynchus ligustici (Linnaeus, 1758)",
      "url": "https://inpn.mnhn.fr/espece/cd_nom/13096"
    }
,
    {
      "name": "Curculio collaris Fabricius, 1792",
      "url": "https://inpn.mnhn.fr/espece/cd_nom/409532"
    }
,
    {
      "name": "Curculio levistici Müller, 1776",
      "url": "https://inpn.mnhn.fr/espece/cd_nom/409529"
    }
,
    {
      "name": "Curculio ligustici Linnaeus, 1758",
      "url": "https://inpn.mnhn.fr/espece/cd_nom/803572"
    }
,
    {
      "name": "Curculio monopterus Fourcoy, 1776",
      "url": "https://inpn.mnhn.fr/espece/cd_nom/409530"
    }
,
    {
      "name": "Curculio muelleri Gmelin, 1790",
      "url": "https://inpn.mnhn.fr/espece/cd_nom/409531"
    }
,
    {
      "name": "Curculio rugosus Schrank, 1798",
      "url": "https://inpn.mnhn.fr/espece/cd_nom/409533"
    }
,
    {
      "name": "Liophloeus brucki Bach, 1854",
      "url": "https://inpn.mnhn.fr/espece/cd_nom/409535"
    }
,
    {
      "name": "Otiorhynchus agnathus ",
      "url": "https://inpn.mnhn.fr/espece/cd_nom/13100"
    }
,
    {
      "name": "Otiorhynchus agnatus Gyllenhal, 1834",
      "url": "https://inpn.mnhn.fr/espece/cd_nom/409534"
    }
,
    {
      "name": "Otiorhynchus asper F. Solari, 1932",
      "url": "https://inpn.mnhn.fr/espece/cd_nom/409538"
    }
,
    {
      "name": "Otiorhynchus brachypterus F. Solari, 1932",
      "url": "https://inpn.mnhn.fr/espece/cd_nom/409539"
    }
,
    {
      "name": "Otiorhynchus comes F. Solari, 1932",
      "url": "https://inpn.mnhn.fr/espece/cd_nom/409540"
    }
,
    {
      "name": "Otiorhynchus debilicornis F. Solari, 1932",
      "url": "https://inpn.mnhn.fr/espece/cd_nom/409541"
    }
,
    {
      "name": "Otiorhynchus hormuzakii Penecke, 1935",
      "url": "https://inpn.mnhn.fr/espece/cd_nom/409547"
    }
,
    {
      "name": "Otiorhynchus (Arammichnus) ligustici ",
      "url": "https://inpn.mnhn.fr/espece/cd_nom/13097"
    }
,
    {
      "name": "Otiorhynchus incertus F. Solari, 1832",
      "url": "https://inpn.mnhn.fr/espece/cd_nom/409543"
    }
,
    {
      "name": "Otiorhynchus lederei ",
      "url": "https://inpn.mnhn.fr/espece/cd_nom/13101"
    }
,
    {
      "name": "Otiorhynchus ledereri Stierlin, 1873",
      "url": "https://inpn.mnhn.fr/espece/cd_nom/409536"
    }
,
    {
      "name": "Otiorhynchus muticus F. Solari, 1832",
      "url": "https://inpn.mnhn.fr/espece/cd_nom/409542"
    }
,
    {
      "name": "Otiorhynchus polonicus F. Solari, 1932",
      "url": "https://inpn.mnhn.fr/espece/cd_nom/409544"
    }
,
    {
      "name": "Otiorhynchus similis F. Solari, 1932",
      "url": "https://inpn.mnhn.fr/espece/cd_nom/409545"
    }
,
    {
      "name": "Otiorhynchus vicarius F. Solari, 1832",
      "url": "https://inpn.mnhn.fr/espece/cd_nom/409546"
    }
,
    {
      "name": "Otiorhynchus xanthotrichus Apfelbeck, 1922",
      "url": "https://inpn.mnhn.fr/espece/cd_nom/409537"
    }
,
    {
      "name": "Otiorhynchus lirus Schönherr, 1834",
      "url": "https://inpn.mnhn.fr/espece/cd_nom/794928"
    }
,
    {
      "name": "Curculio laevigatus Fabricius, 1792",
      "url": "https://inpn.mnhn.fr/espece/cd_nom/803580"
    }
,
    {
      "name": "Otiorhynchus cornicinus Stierlin, 1861",
      "url": "https://inpn.mnhn.fr/espece/cd_nom/409372"
    }
,
    {
      "name": "Otiorhynchus laevigatus (Fabricius, 1792)",
      "url": "https://inpn.mnhn.fr/espece/cd_nom/12408"
    }
,
    {
      "name": "Otiorhynchus levigatus Schönherr, 1843",
      "url": "https://inpn.mnhn.fr/espece/cd_nom/409371"
    }
,
    {
      "name": "Otiorhynchus loevigatus Grenier, 1863",
      "url": "https://inpn.mnhn.fr/espece/cd_nom/409373"
    }
,
    {
      "name": "Otiorhynchus lugdunensis Boheman, 1842",
      "url": "https://inpn.mnhn.fr/espece/cd_nom/409399"
    }
,
    {
      "name": "Otiorhynchus dilatipes Guillebeau, 1885",
      "url": "https://inpn.mnhn.fr/espece/cd_nom/409406"
    }
,
    {
      "name": "Otiorhynchus elongatus Stierlin, 1861",
      "url": "https://inpn.mnhn.fr/espece/cd_nom/13054"
    }
,
    {
      "name": "Otiorhynchus francolinus Schaufuss, 1867",
      "url": "https://inpn.mnhn.fr/espece/cd_nom/409403"
    }
,
    {
      "name": "Otiorhynchus guillebeaui Desbrochers, 1894",
      "url": "https://inpn.mnhn.fr/espece/cd_nom/409408"
    }
,
    {
      "name": "Otiorhynchus longulus Marseul, 1871",
      "url": "https://inpn.mnhn.fr/espece/cd_nom/409405"
    }
,
    {
      "name": "Otiorhynchus lutosus Stierlin, 1858",
      "url": "https://inpn.mnhn.fr/espece/cd_nom/13071"
    }
,
    {
      "name": "Otiorhynchus (Dorymerus) lutosus ",
      "url": "https://inpn.mnhn.fr/espece/cd_nom/13072"
    }
,
    {
      "name": "Otiorhynchus malefidus Gyllenhal, 1834",
      "url": "https://inpn.mnhn.fr/espece/cd_nom/12410"
    }
,
    {
      "name": "Otiorhynchus planidorsis Fairmaire, 1857",
      "url": "https://inpn.mnhn.fr/espece/cd_nom/12411"
    }
,
    {
      "name": "Otiorhynchus planidorsis Fairmaire, 1956",
      "url": "https://inpn.mnhn.fr/espece/cd_nom/409426"
    }
,
    {
      "name": "Otiorhynchus planidorsis Stierli",
      "url": "https://inpn.mnhn.fr/espece/cd_nom/13056"
    }
,
    {
      "name": "Otiorhynchus praelongus Fairmaire, 1863",
      "url": "https://inpn.mnhn.fr/espece/cd_nom/12412"
    }
,
    {
      "name": "Otiorhynchus martinii (Fairmaire, 1862)",
      "url": "https://inpn.mnhn.fr/espece/cd_nom/242574"
    }
,
    {
      "name": "Troglorhynchus martini Fairmaire, 1862",
      "url": "https://inpn.mnhn.fr/espece/cd_nom/13122"
    }
,
    {
      "name": "Otiorhynchus mayetii (Fairmaire, 1878)",
      "url": "https://inpn.mnhn.fr/espece/cd_nom/794923"
    }
,
    {
      "name": "Troglorhynchus mayeti Fairmaire, 1878",
      "url": "https://inpn.mnhn.fr/espece/cd_nom/409491"
    }
,
    {
      "name": "Otiorhynchus meridionalis Gyllenhal, 1834",
      "url": "https://inpn.mnhn.fr/espece/cd_nom/11804"
    }
,
    {
      "name": "Otiorhynchus civis Stierlin, 1861",
      "url": "https://inpn.mnhn.fr/espece/cd_nom/11807"
    }
,
    {
      "name": "Otiorhynchus olae Stierlin",
      "url": "https://inpn.mnhn.fr/espece/cd_nom/11806"
    }
,
    {
      "name": "Otiorhynchus oleae Stierlin, 1861",
      "url": "https://inpn.mnhn.fr/espece/cd_nom/409375"
    }
,
    {
      "name": "Otiorhynchus peyrissaci Stierlin, 1886",
      "url": "https://inpn.mnhn.fr/espece/cd_nom/409376"
    }
,
    {
      "name": "Otiorhynchus subglobosus Blanchard, 1851",
      "url": "https://inpn.mnhn.fr/espece/cd_nom/409377"
    }
,
    {
      "name": "Otiorhynchus subvestitus Reitter, 1913",
      "url": "https://inpn.mnhn.fr/espece/cd_nom/409378"
    }
,
    {
      "name": "Otiorynchus meridionalis Gyllenhal, 1834",
      "url": "https://inpn.mnhn.fr/espece/cd_nom/1014874"
    }
,
    {
      "name": "Otiorhynchus misellus Stierlin, 1861",
      "url": "https://inpn.mnhn.fr/espece/cd_nom/12454"
    }
,
    {
      "name": "Otiorhynchus moestus Gyllenhal, 1834",
      "url": "https://inpn.mnhn.fr/espece/cd_nom/13052"
    }
,
    {
      "name": "Otiorhynchus grandifrons Reitter, 1898",
      "url": "https://inpn.mnhn.fr/espece/cd_nom/409508"
    }
,
    {
      "name": "Otiorhynchus (Dorymerus) moestus ",
      "url": "https://inpn.mnhn.fr/espece/cd_nom/13053"
    }
,
    {
      "name": "Otiorhynchus planidorsis Stierlin, 1886",
      "url": "https://inpn.mnhn.fr/espece/cd_nom/409507"
    }
,
    {
      "name": "Otiorhynchus pseudocoriarius F. Solari, 1950",
      "url": "https://inpn.mnhn.fr/espece/cd_nom/409509"
    }
,
    {
      "name": "Otiorhynchus raymondi Gaut.",
      "url": "https://inpn.mnhn.fr/espece/cd_nom/13055"
    }
,
    {
      "name": "Otiorhynchus raymondi Gauthier, 1860",
      "url": "https://inpn.mnhn.fr/espece/cd_nom/409506"
    }
,
    {
      "name": "Otiorrhynchus grandifrons Reitter, 1898",
      "url": "https://inpn.mnhn.fr/espece/cd_nom/1018821"
    }
,
    {
      "name": "Otiorhynchus morio (Fabricius, 1781)",
      "url": "https://inpn.mnhn.fr/espece/cd_nom/242564"
    }
,
    {
      "name": "Curculio morio Fabricius, 1781",
      "url": "https://inpn.mnhn.fr/espece/cd_nom/803584"
    }
,
    {
      "name": "Otiorhynchus morio cabroli Costessèque, 2007",
      "url": "https://inpn.mnhn.fr/espece/cd_nom/795765"
    }
,
    {
      "name": "Otiorhynchus morio diversesculptus Pic, 1920",
      "url": "https://inpn.mnhn.fr/espece/cd_nom/252860"
    }
,
    {
      "name": "Otiorrhynchus navaricus var. diversesculptus Pic, 1920",
      "url": "https://inpn.mnhn.fr/espece/cd_nom/884884"
    }
,
    {
      "name": "Otiorhynchus morio morio (Fabricius, 1781)",
      "url": "https://inpn.mnhn.fr/espece/cd_nom/252859"
    }
,
    {
      "name": "Curculio unicolor Herbst, 1795",
      "url": "https://inpn.mnhn.fr/espece/cd_nom/409427"
    }
,
    {
      "name": "Otiorhynchus ebeninus Gyllenhal, 1834",
      "url": "https://inpn.mnhn.fr/espece/cd_nom/409428"
    }
,
    {
      "name": "Otiorhynchus imus Boheman, 1843",
      "url": "https://inpn.mnhn.fr/espece/cd_nom/409430"
    }
,
    {
      "name": "Otiorhynchus memnonius Gyllenhal, 1834",
      "url": "https://inpn.mnhn.fr/espece/cd_nom/409429"
    }
,
    {
      "name": "Otiorhynchus morio navaricus Gyllenhal, 1834",
      "url": "https://inpn.mnhn.fr/espece/cd_nom/252861"
    }
,
    {
      "name": "Otiorhynchus hispanus Stierlin, 1862",
      "url": "https://inpn.mnhn.fr/espece/cd_nom/409431"
    }
,
    {
      "name": "Otiorhynchus intricatus Stierlin, 1866",
      "url": "https://inpn.mnhn.fr/espece/cd_nom/409433"
    }
,
    {
      "name": "Otiorhynchus navaricus Gyllenhal, 1834",
      "url": "https://inpn.mnhn.fr/espece/cd_nom/982978"
    }
,
    {
      "name": "Otiorhynchus nitidicollis Dufour, 1851",
      "url": "https://inpn.mnhn.fr/espece/cd_nom/409432"
    }
,
    {
      "name": "Otiorhynchus morio sublaevigatus Zumpt, 1934",
      "url": "https://inpn.mnhn.fr/espece/cd_nom/793187"
    }
,
    {
      "name": "Otiorhynchus morio sublaevigatus Reitter, 1913",
      "url": "https://inpn.mnhn.fr/espece/cd_nom/252862"
    }
,
    {
      "name": "Otiorhynchus nicaeicivis (Gozis, 1895)",
      "url": "https://inpn.mnhn.fr/espece/cd_nom/794924"
    }
,
    {
      "name": "Traglorhynchus nicaecivis Gozis, 1895",
      "url": "https://inpn.mnhn.fr/espece/cd_nom/409490"
    }
,
    {
      "name": "Troglorrhynchus nicaecivis Gozis, 1895",
      "url": "https://inpn.mnhn.fr/espece/cd_nom/884883"
    }
,
    {
      "name": "Otiorhynchus nodosus (O.F. Müller, 1764)",
      "url": "https://inpn.mnhn.fr/espece/cd_nom/12424"
    }
,
    {
      "name": "Curculio dubius Ström, 1765",
      "url": "https://inpn.mnhn.fr/espece/cd_nom/409436"
    }
,
    {
      "name": "Curculio maurus Gyllenhal, 1813",
      "url": "https://inpn.mnhn.fr/espece/cd_nom/409439"
    }
,
    {
      "name": "Curculio morio Bonsdorff, 1785",
      "url": "https://inpn.mnhn.fr/espece/cd_nom/409438"
    }
,
    {
      "name": "Curculio nodosus O.F. Müller, 1764",
      "url": "https://inpn.mnhn.fr/espece/cd_nom/803587"
    }
,
    {
      "name": "Curculo sulcatus Paykull, 1800",
      "url": "https://inpn.mnhn.fr/espece/cd_nom/409437"
    }
,
    {
      "name": "Otiorhynchus aurosus Mulsant & Rey, 1859",
      "url": "https://inpn.mnhn.fr/espece/cd_nom/409445"
    }
,
    {
      "name": "Otiorhynchus bructeri Germar, 1823",
      "url": "https://inpn.mnhn.fr/espece/cd_nom/798431"
    }
,
    {
      "name": "Otiorhynchus capreae Stierlin, 1861",
      "url": "https://inpn.mnhn.fr/espece/cd_nom/409446"
    }
,
    {
      "name": "Otiorhynchus comosellus Boheman, 1843",
      "url": "https://inpn.mnhn.fr/espece/cd_nom/409441"
    }
,
    {
      "name": "Otiorhynchus demotus Boheman, 1843",
      "url": "https://inpn.mnhn.fr/espece/cd_nom/409442"
    }
,
    {
      "name": "Otiorhynchus dubius Ström, 1765",
      "url": "https://inpn.mnhn.fr/espece/cd_nom/719593"
    }
,
    {
      "name": "Otiorhynchus gelidus Gistel, 1857",
      "url": "https://inpn.mnhn.fr/espece/cd_nom/409443"
    }
,
    {
      "name": "Otiorhynchus gobanzi Gredler, 1868",
      "url": "https://inpn.mnhn.fr/espece/cd_nom/409451"
    }
,
    {
      "name": "Otiorhynchus pauper Boheman, 1843",
      "url": "https://inpn.mnhn.fr/espece/cd_nom/409440"
    }
,
    {
      "name": "Otiorhynchus pertusus Stierlin, 1862",
      "url": "https://inpn.mnhn.fr/espece/cd_nom/409447"
    }
,
    {
      "name": "Otiorhynchus pseudopauper Reitter, 1913",
      "url": "https://inpn.mnhn.fr/espece/cd_nom/409449"
    }
,
    {
      "name": "Otiorhynchus tournieri Stierlin, 1875",
      "url": "https://inpn.mnhn.fr/espece/cd_nom/409448"
    }
,
    {
      "name": "Otiorhynchus vulgaris Marseul, 1872",
      "url": "https://inpn.mnhn.fr/espece/cd_nom/409450"
    }
,
    {
      "name": "Otiorhynchus wiesurii Stierlin, 1858",
      "url": "https://inpn.mnhn.fr/espece/cd_nom/409444"
    }
,
    {
      "name": "Otiorhynchus noui Fairmaire, 1862",
      "url": "https://inpn.mnhn.fr/espece/cd_nom/12414"
    }
,
    {
      "name": "Otiorhynchus nubilus Boheman, 1842",
      "url": "https://inpn.mnhn.fr/espece/cd_nom/13049"
    }
,
    {
      "name": "Otiorhynchus nubilus nubilus Boheman, 1842",
      "url": "https://inpn.mnhn.fr/espece/cd_nom/795761"
    }
,
    {
      "name": "Otiorhynchus bischoffi Stierlin",
      "url": "https://inpn.mnhn.fr/espece/cd_nom/13051"
    }
,
    {
      "name": "Otiorhynchus bischoffi Stierlin, 1858",
      "url": "https://inpn.mnhn.fr/espece/cd_nom/409499"
    }
,
    {
      "name": "Otiorhynchus partitialis Boheman, 1843",
      "url": "https://inpn.mnhn.fr/espece/cd_nom/409498"
    }
,
    {
      "name": "Otiorhynchus ovatus (Linnaeus, 1758)",
      "url": "https://inpn.mnhn.fr/espece/cd_nom/13088"
    }
,
    {
      "name": "Curculio ovatus Linnaeus, 1758",
      "url": "https://inpn.mnhn.fr/espece/cd_nom/803582"
    }
,
    {
      "name": "Otiorhynchus (Tournieria) ovatus ",
      "url": "https://inpn.mnhn.fr/espece/cd_nom/13089"
    }
,
    {
      "name": "Otiorhynchus ovatus ovatus (Linnaeus, 1758)",
      "url": "https://inpn.mnhn.fr/espece/cd_nom/252873"
    }
,
    {
      "name": "Curculio pabulinus Panzer, 1798",
      "url": "https://inpn.mnhn.fr/espece/cd_nom/409566"
    }
,
    {
      "name": "Curculio rosae De Geer, 1775",
      "url": "https://inpn.mnhn.fr/espece/cd_nom/409565"
    }
,
    {
      "name": "Curculio rufipes Scopoli, 1763",
      "url": "https://inpn.mnhn.fr/espece/cd_nom/409564"
    }
,
    {
      "name": "Curculio scopolii Poda, 1762",
      "url": "https://inpn.mnhn.fr/espece/cd_nom/409563"
    }
,
    {
      "name": "Otiorhynchus globulipennis Gyllenhal, 1834",
      "url": "https://inpn.mnhn.fr/espece/cd_nom/409568"
    }
,
    {
      "name": "Otiorhynchus vorticosus Gyllenhal, 1834",
      "url": "https://inpn.mnhn.fr/espece/cd_nom/409567"
    }
,
    {
      "name": "Otiorhynchus paradisiacus Pesarini, 1968",
      "url": "https://inpn.mnhn.fr/espece/cd_nom/11813"
    }
,
    {
      "name": "Otiorhynchus pascuorum Peyerimhoff, 1901",
      "url": "https://inpn.mnhn.fr/espece/cd_nom/11820"
    }
,
    {
      "name": "Brachyrrhinus pascuorum Peyerimhoff, 1901",
      "url": "https://inpn.mnhn.fr/espece/cd_nom/803585"
    }
,
    {
      "name": "Otiorhynchus pauxillus Rosenhauer, 1847",
      "url": "https://inpn.mnhn.fr/espece/cd_nom/13079"
    }
,
    {
      "name": "Otiorhynchus hampei Stierlin",
      "url": "https://inpn.mnhn.fr/espece/cd_nom/13082"
    }
,
    {
      "name": "Otiorhynchus hampei Stierlin, 1961",
      "url": "https://inpn.mnhn.fr/espece/cd_nom/409551"
    }
,
    {
      "name": "Otiorhynchus (Tournieria) pauxillus ",
      "url": "https://inpn.mnhn.fr/espece/cd_nom/13080"
    }
,
    {
      "name": "Otiorhynchus pygmaeus Stierlin, 1883",
      "url": "https://inpn.mnhn.fr/espece/cd_nom/409554"
    }
,
    {
      "name": "Otiorhynchus rubiginosus Stierlin, 1861",
      "url": "https://inpn.mnhn.fr/espece/cd_nom/409553"
    }
,
    {
      "name": "Otiorhynchus rugirostris Stierlin",
      "url": "https://inpn.mnhn.fr/espece/cd_nom/13081"
    }
,
    {
      "name": "Otiorhynchus rugirostris Stierlin, 1879",
      "url": "https://inpn.mnhn.fr/espece/cd_nom/409552"
    }
,
    {
      "name": "Otiorhynchus pedemontanus Stierlin, 1861",
      "url": "https://inpn.mnhn.fr/espece/cd_nom/13059"
    }
,
    {
      "name": "Otiorhynchus (Dorymerus) pedemontanus ",
      "url": "https://inpn.mnhn.fr/espece/cd_nom/13060"
    }
,
    {
      "name": "Otiorhynchus peyerimhoffi Hustache, 1920",
      "url": "https://inpn.mnhn.fr/espece/cd_nom/11816"
    }
,
    {
      "name": "Otiorrhynchus peyerimhoffi Hustache, 1920",
      "url": "https://inpn.mnhn.fr/espece/cd_nom/978976"
    }
,
    {
      "name": "Otiorhynchus porcatus (Herbst, 1795)",
      "url": "https://inpn.mnhn.fr/espece/cd_nom/12436"
    }
,
    {
      "name": "Brachyrhinus sexcostatus Latreille, 1804",
      "url": "https://inpn.mnhn.fr/espece/cd_nom/409457"
    }
,
    {
      "name": "Curculio costatus Fabricius, 1801",
      "url": "https://inpn.mnhn.fr/espece/cd_nom/409455"
    }
,
    {
      "name": "Curculio porcatus Herbst, 1795",
      "url": "https://inpn.mnhn.fr/espece/cd_nom/803574"
    }
,
    {
      "name": "Curculio senex Olivier, 1807",
      "url": "https://inpn.mnhn.fr/espece/cd_nom/409456"
    }
,
    {
      "name": "Thylacites porcatus Sturm, 1826",
      "url": "https://inpn.mnhn.fr/espece/cd_nom/409458"
    }
,
    {
      "name": "Otiorhynchus pourtoyi Tempère, 1972",
      "url": "https://inpn.mnhn.fr/espece/cd_nom/12413"
    }
,
    {
      "name": "Otiorhynchus pourtoyi aubryi Tempère, 1972",
      "url": "https://inpn.mnhn.fr/espece/cd_nom/252863"
    }
,
    {
      "name": "Otiorhynchus pourtoyi pourtoyi Tempère, 1972",
      "url": "https://inpn.mnhn.fr/espece/cd_nom/252864"
    }
,
    {
      "name": "Otiorhynchus procerus Stierlin, 1875",
      "url": "https://inpn.mnhn.fr/espece/cd_nom/13025"
    }
,
    {
      "name": "Otiorhynchus cazorlae Roudier, 1959",
      "url": "https://inpn.mnhn.fr/espece/cd_nom/798426"
    }
,
    {
      "name": "Otiorhynchus procerus procerus Stierlin, 1875",
      "url": "https://inpn.mnhn.fr/espece/cd_nom/252868"
    }
,
    {
      "name": "Otiorhynchus (Dorymerus) procerus ",
      "url": "https://inpn.mnhn.fr/espece/cd_nom/13026"
    }
,
    {
      "name": "Otiorhynchus pseudonothus Apfelbeck, 1897",
      "url": "https://inpn.mnhn.fr/espece/cd_nom/409337"
    }
,
    {
      "name": "Otiorhynchus apenninus Stierlin, 1883",
      "url": "https://inpn.mnhn.fr/espece/cd_nom/242552"
    }
,
    {
      "name": "Otiorhynchus salicicola Heyden, 1908",
      "url": "https://inpn.mnhn.fr/espece/cd_nom/11799"
    }
,
    {
      "name": "Otiorhynchus salicis Stierlin, 1858",
      "url": "https://inpn.mnhn.fr/espece/cd_nom/728035"
    }
,
    {
      "name": "Otiorrhynchus liguricus Apfelbeck, 1897",
      "url": "https://inpn.mnhn.fr/espece/cd_nom/409336"
    }
,
    {
      "name": "Otiorrhynchus salicicola Heyden, 1908",
      "url": "https://inpn.mnhn.fr/espece/cd_nom/409335"
    }
,
    {
      "name": "Otiorrhynchus salicis Stierlin, 1858",
      "url": "https://inpn.mnhn.fr/espece/cd_nom/409334"
    }
,
    {
      "name": "Otiorhynchus pupillatus Gyllenhal, 1834",
      "url": "https://inpn.mnhn.fr/espece/cd_nom/13027"
    }
,
    {
      "name": "Otiorhynchus (Dorymerus) pupillatus ",
      "url": "https://inpn.mnhn.fr/espece/cd_nom/13028"
    }
,
    {
      "name": "Otiorhynchus sabaudus F. Solari, 1947",
      "url": "https://inpn.mnhn.fr/espece/cd_nom/409475"
    }
,
    {
      "name": "Otiorhynchus subdentatus Stierlin, 1858",
      "url": "https://inpn.mnhn.fr/espece/cd_nom/798427"
    }
,
    {
      "name": "Otiorhynchus pusillus Stierlin, 1861",
      "url": "https://inpn.mnhn.fr/espece/cd_nom/12458"
    }
,
    {
      "name": "Otiorhynchus (Dormerus) pusillus ",
      "url": "https://inpn.mnhn.fr/espece/cd_nom/12459"
    }
,
    {
      "name": "Otiorhynchus pusillus cottianus Magnano, 1967",
      "url": "https://inpn.mnhn.fr/espece/cd_nom/252869"
    }
,
    {
      "name": "Otiorhynchus pusillus pusillus Stierlin, 1861",
      "url": "https://inpn.mnhn.fr/espece/cd_nom/252870"
    }
,
    {
      "name": "Otiorhynchus putoni Stierlin, 1891",
      "url": "https://inpn.mnhn.fr/espece/cd_nom/11818"
    }
,
    {
      "name": "Otiorhynchus putoni dissimilis Hoffmann, 1950",
      "url": "https://inpn.mnhn.fr/espece/cd_nom/252865"
    }
,
    {
      "name": "Otiorhynchus putoni putoni Stierlin, 1891",
      "url": "https://inpn.mnhn.fr/espece/cd_nom/252866"
    }
,
    {
      "name": "Otiorhynchus pyrenaeus Gyllenhal, 1834",
      "url": "https://inpn.mnhn.fr/espece/cd_nom/12978"
    }
,
    {
      "name": "Otiorhynchus pyrenaeus occidentalis Hustache, 1923",
      "url": "https://inpn.mnhn.fr/espece/cd_nom/252854"
    }
,
    {
      "name": "Otiorhynchus pyrenaeus pyrenaeus Gyllenhal, 1834",
      "url": "https://inpn.mnhn.fr/espece/cd_nom/252853"
    }
,
    {
      "name": "Otiorhynchus femoralis Boheman, 1843",
      "url": "https://inpn.mnhn.fr/espece/cd_nom/409379"
    }
,
    {
      "name": "Otiorhynchus granuliger Dufour, 1843",
      "url": "https://inpn.mnhn.fr/espece/cd_nom/409380"
    }
,
    {
      "name": "Otiorhynchus hustachei Hoffmann, 1950",
      "url": "https://inpn.mnhn.fr/espece/cd_nom/409381"
    }
,
    {
      "name": "Otiorhynchus travnikanus Stierlin, 1891",
      "url": "https://inpn.mnhn.fr/espece/cd_nom/11798"
    }
,
    {
      "name": "Otiorhynchus raucus (Fabricius, 1777)",
      "url": "https://inpn.mnhn.fr/espece/cd_nom/12428"
    }
,
    {
      "name": "Brachyrhinus luctuosus Latreille, 1804",
      "url": "https://inpn.mnhn.fr/espece/cd_nom/409558"
    }
,
    {
      "name": "Curculio arenarius Herbst, 1784",
      "url": "https://inpn.mnhn.fr/espece/cd_nom/409556"
    }
,
    {
      "name": "Curculio fulvus Fabricius, 1787",
      "url": "https://inpn.mnhn.fr/espece/cd_nom/409557"
    }
,
    {
      "name": "Curculio raucus Fabricius, 1777",
      "url": "https://inpn.mnhn.fr/espece/cd_nom/803571"
    }
,
    {
      "name": "Curculio tristis Fabricius, 1775",
      "url": "https://inpn.mnhn.fr/espece/cd_nom/409555"
    }
,
    {
      "name": "Otiorhynchus bettinii Fiori, 1949",
      "url": "https://inpn.mnhn.fr/espece/cd_nom/409559"
    }
,
    {
      "name": "Otiorhynchus raucus raucus (Fabricius, 1777)",
      "url": "https://inpn.mnhn.fr/espece/cd_nom/252872"
    }
,
    {
      "name": "Otiorhynchus tristis (Scopoli, 1763)",
      "url": "https://inpn.mnhn.fr/espece/cd_nom/327048"
    }
,
    {
      "name": "Otiorhynchus rugifrons (Gyllenhal, 1813)",
      "url": "https://inpn.mnhn.fr/espece/cd_nom/13061"
    }
,
    {
      "name": "Curculio rugifrons Gyllenhal, 1813",
      "url": "https://inpn.mnhn.fr/espece/cd_nom/803589"
    }
,
    {
      "name": "Otiorhynchus ambiguus Schönherr, 1843",
      "url": "https://inpn.mnhn.fr/espece/cd_nom/409513"
    }
,
    {
      "name": "Otiorhynchus dillwynii Stephens, 1831",
      "url": "https://inpn.mnhn.fr/espece/cd_nom/409510"
    }
,
    {
      "name": "Otiorhynchus ghestleri Stierlin",
      "url": "https://inpn.mnhn.fr/espece/cd_nom/13063"
    }
,
    {
      "name": "Otiorhynchus ghestleri Stierlin, 1861",
      "url": "https://inpn.mnhn.fr/espece/cd_nom/409515"
    }
,
    {
      "name": "Otiorhynchus (Dorymerus) rugifrons ",
      "url": "https://inpn.mnhn.fr/espece/cd_nom/13062"
    }
,
    {
      "name": "Otiorhynchus impoticus Boheman, 1843",
      "url": "https://inpn.mnhn.fr/espece/cd_nom/409514"
    }
,
    {
      "name": "Otiorhynchus piochardi Stierlin, 1866",
      "url": "https://inpn.mnhn.fr/espece/cd_nom/409517"
    }
,
    {
      "name": "Otiorhynchus rugicollis Stephens, 1831",
      "url": "https://inpn.mnhn.fr/espece/cd_nom/409511"
    }
,
    {
      "name": "Otiorhynchus scaber Stephens, 1831",
      "url": "https://inpn.mnhn.fr/espece/cd_nom/409512"
    }
,
    {
      "name": "Otiorhynchus senex Stierlin, 1861",
      "url": "https://inpn.mnhn.fr/espece/cd_nom/409516"
    }
,
    {
      "name": "Otiorhynchus rugosostriatus (Goeze, 1777)",
      "url": "https://inpn.mnhn.fr/espece/cd_nom/12430"
    }
,
    {
      "name": "Curculio corrugatus Gmelin, 1790",
      "url": "https://inpn.mnhn.fr/espece/cd_nom/409453"
    }
,
    {
      "name": "Curculio rugosissimus Villers, 1789",
      "url": "https://inpn.mnhn.fr/espece/cd_nom/409452"
    }
,
    {
      "name": "Curculio rugosostriatus Goeze, 1777",
      "url": "https://inpn.mnhn.fr/espece/cd_nom/803591"
    }
,
    {
      "name": "Curculio scabrosus Marsham, 1802",
      "url": "https://inpn.mnhn.fr/espece/cd_nom/409454"
    }
,
    {
      "name": "Otiorhynchus rugostriatus (Goeze, 1777)",
      "url": "https://inpn.mnhn.fr/espece/cd_nom/886468"
    }
,
    {
      "name": "Otiorhynchus scabrosus (Marsham, 1802)",
      "url": "https://inpn.mnhn.fr/espece/cd_nom/975068"
    }
,
    {
      "name": "Otiorhynchus sanguinipes Boheman, 1842",
      "url": "https://inpn.mnhn.fr/espece/cd_nom/409400"
    }
,
    {
      "name": "Curculio morio Paykull, 1792",
      "url": "https://inpn.mnhn.fr/espece/cd_nom/409389"
    }
,
    {
      "name": "Curculio niger Marsham, 1801",
      "url": "https://inpn.mnhn.fr/espece/cd_nom/409391"
    }
,
    {
      "name": "Otiorhynchus alsaticus Silbermann, 1833",
      "url": "https://inpn.mnhn.fr/espece/cd_nom/409395"
    }
,
    {
      "name": "Otiorhynchus bavaricus Reitter, 1913",
      "url": "https://inpn.mnhn.fr/espece/cd_nom/409409"
    }
,
    {
      "name": "Otiorhynchus duplicatus F. Solari, 1940",
      "url": "https://inpn.mnhn.fr/espece/cd_nom/409413"
    }
,
    {
      "name": "Otiorhynchus francollinus Guillebeau, 1892",
      "url": "https://inpn.mnhn.fr/espece/cd_nom/409407"
    }
,
    {
      "name": "Otiorhynchus haematopus Stierlin, 1858",
      "url": "https://inpn.mnhn.fr/espece/cd_nom/409401"
    }
,
    {
      "name": "Otiorhynchus heynei Voss, 1919",
      "url": "https://inpn.mnhn.fr/espece/cd_nom/409411"
    }
,
    {
      "name": "Otiorhynchus stierlinianus Uyttenboogaart, 1933",
      "url": "https://inpn.mnhn.fr/espece/cd_nom/409416"
    }
,
    {
      "name": "Otiorhynchus stierlini Uyttenboogaart, 1931",
      "url": "https://inpn.mnhn.fr/espece/cd_nom/409415"
    }
,
    {
      "name": "Otiorhynchus substriata Hustache, 1923",
      "url": "https://inpn.mnhn.fr/espece/cd_nom/409412"
    }
,
    {
      "name": "Otiorhynchus ungensis Csiki, 1942",
      "url": "https://inpn.mnhn.fr/espece/cd_nom/409417"
    }
,
    {
      "name": "Pachygaster biturigensis Dejean, 1821",
      "url": "https://inpn.mnhn.fr/espece/cd_nom/409393"
    }
,
    {
      "name": "Pachygaster pedemontanus Dejean, 1821",
      "url": "https://inpn.mnhn.fr/espece/cd_nom/409394"
    }
,
    {
      "name": "Otiorhynchus schaeferi Hoffmann, 1961",
      "url": "https://inpn.mnhn.fr/espece/cd_nom/242569"
    }
,
    {
      "name": "Otiorhynchus schaeferi Hoffmman, 1961",
      "url": "https://inpn.mnhn.fr/espece/cd_nom/12452"
    }
,
    {
      "name": "Otiorhynchus sellae Stierlin, 1881",
      "url": "https://inpn.mnhn.fr/espece/cd_nom/795251"
    }
,
    {
      "name": "Otiorhynchus sellae sellae Stierlin, 1881",
      "url": "https://inpn.mnhn.fr/espece/cd_nom/795763"
    }
,
    {
      "name": "Otiorhynchus griseopunctatus sellae Stierlin, 1881",
      "url": "https://inpn.mnhn.fr/espece/cd_nom/326562"
    }
,
    {
      "name": "Otiorhynchus sellae vesulianus Reitter, 1913",
      "url": "https://inpn.mnhn.fr/espece/cd_nom/795764"
    }
,
    {
      "name": "Otiorhynchus clavipes Boheman, 1843",
      "url": "https://inpn.mnhn.fr/espece/cd_nom/409367"
    }
,
    {
      "name": "Otiorhynchus griseopunctatus griseopunctatus Boheman, 1843",
      "url": "https://inpn.mnhn.fr/espece/cd_nom/252852"
    }
,
    {
      "name": "Otiorhynchus griseopunctatus Boheman, 1843",
      "url": "https://inpn.mnhn.fr/espece/cd_nom/11812"
    }
,
    {
      "name": "Otiorhynchus insubricus Zumpt, 1933",
      "url": "https://inpn.mnhn.fr/espece/cd_nom/409369"
    }
,
    {
      "name": "Otiorhynchus joachim Merceron, 1994",
      "url": "https://inpn.mnhn.fr/espece/cd_nom/798428"
    }
,
    {
      "name": "Otiorhynchus peirolerii Stierlin, 1861",
      "url": "https://inpn.mnhn.fr/espece/cd_nom/409368"
    }
,
    {
      "name": "Otiorhynchus reitzei Zumpt, 1933",
      "url": "https://inpn.mnhn.fr/espece/cd_nom/409370"
    }
,
    {
      "name": "Otiorhynchus seriehispidus Stierlin, 1872",
      "url": "https://inpn.mnhn.fr/espece/cd_nom/12419"
    }
,
    {
      "name": "Otiorhynchus mascarauxi Roudier, 1977",
      "url": "https://inpn.mnhn.fr/espece/cd_nom/12421"
    }
,
    {
      "name": "Otiorhynchus seriehirtus Marseul, 1872",
      "url": "https://inpn.mnhn.fr/espece/cd_nom/432068"
    }
,
    {
      "name": "Otiorhynchus simoni Bedel, 1874",
      "url": "https://inpn.mnhn.fr/espece/cd_nom/242565"
    }
,
    {
      "name": "Otiorhynchus singularis (Linnaeus, 1767)",
      "url": "https://inpn.mnhn.fr/espece/cd_nom/13015"
    }
,
    {
      "name": "Curculio singularis Linnaeus, 1767",
      "url": "https://inpn.mnhn.fr/espece/cd_nom/803575"
    }
,
    {
      "name": "Otiorhynchus chevrolati Gyllenhal, 1843",
      "url": "https://inpn.mnhn.fr/espece/cd_nom/409483"
    }
,
    {
      "name": "Otiorhynchus corniculatus Reitter, 1914",
      "url": "https://inpn.mnhn.fr/espece/cd_nom/409484"
    }
,
    {
      "name": "Otiorhynchus (Dorymerus) singularis ",
      "url": "https://inpn.mnhn.fr/espece/cd_nom/13016"
    }
,
    {
      "name": "Otiorhynchus stomachosus Gyllenhal, 1834",
      "url": "https://inpn.mnhn.fr/espece/cd_nom/242559"
    }
,
    {
      "name": "Otiorhynchus ariasi Stierlin, 1861",
      "url": "https://inpn.mnhn.fr/espece/cd_nom/409384"
    }
,
    {
      "name": "Otiorhynchus nigriceps Stierlin, 1861",
      "url": "https://inpn.mnhn.fr/espece/cd_nom/409385"
    }
,
    {
      "name": "Otiorhynchus nigripes Boheman, 1843",
      "url": "https://inpn.mnhn.fr/espece/cd_nom/409382"
    }
,
    {
      "name": "Otiorhynchus pubens Boheman, 1842",
      "url": "https://inpn.mnhn.fr/espece/cd_nom/798429"
    }
,
    {
      "name": "Otiorhynchus pubeus Boheman, 1843",
      "url": "https://inpn.mnhn.fr/espece/cd_nom/409383"
    }
,
    {
      "name": "Otiorhynchus similis Hoffmann, 1950",
      "url": "https://inpn.mnhn.fr/espece/cd_nom/409386"
    }
,
    {
      "name": "Otiorhynchus stricticollis Fairmaire, 1859",
      "url": "https://inpn.mnhn.fr/espece/cd_nom/11821"
    }
,
    {
      "name": "Otiorhynchus stricticollis juniperi Tempère, 1939",
      "url": "https://inpn.mnhn.fr/espece/cd_nom/252856"
    }
,
    {
      "name": "Otiorhynchus stricticollis stricticollis Fairmaire, 1859",
      "url": "https://inpn.mnhn.fr/espece/cd_nom/252855"
    }
,
    {
      "name": "Otiorhynchus gallicus Stierlin, 1861",
      "url": "https://inpn.mnhn.fr/espece/cd_nom/409387"
    }
,
    {
      "name": "Otiorhynchus subcostatus Stierlin, 1866",
      "url": "https://inpn.mnhn.fr/espece/cd_nom/12438"
    }
,
    {
      "name": "Otiorhynchus subdentatus Bach, 1854",
      "url": "https://inpn.mnhn.fr/espece/cd_nom/242570"
    }
,
    {
      "name": "Otiorhynchus cyclopterus F. Solari, 1947",
      "url": "https://inpn.mnhn.fr/espece/cd_nom/409486"
    }
,
    {
      "name": "Otiorhynchus iridescens F. Solari, 1947",
      "url": "https://inpn.mnhn.fr/espece/cd_nom/409485"
    }
,
    {
      "name": "Otiorhynchus sulcatus (Fabricius, 1775)",
      "url": "https://inpn.mnhn.fr/espece/cd_nom/13044"
    }
,
    {
      "name": "Curculio griseopunctatus De Geer, 1775",
      "url": "https://inpn.mnhn.fr/espece/cd_nom/409493"
    }
,
    {
      "name": "Curculio strictus Gmelin, 1790",
      "url": "https://inpn.mnhn.fr/espece/cd_nom/409494"
    }
,
    {
      "name": "Curculio sulcatus Fabricius, 1775",
      "url": "https://inpn.mnhn.fr/espece/cd_nom/803573"
    }
,
    {
      "name": "Otiorhynchus (Dorymerus) sulcatus (Fabricius, 1775)",
      "url": "https://inpn.mnhn.fr/espece/cd_nom/13047"
    }
,
    {
      "name": "Otiorhynchus linearis Stierlin, 1861",
      "url": "https://inpn.mnhn.fr/espece/cd_nom/409495"
    }
,
    {
      "name": "Otiorhynchus pseudolinearis Reitter, 1914",
      "url": "https://inpn.mnhn.fr/espece/cd_nom/409496"
    }
,
    {
      "name": "Otiorhynchus sayi Boheman, 1843",
      "url": "https://inpn.mnhn.fr/espece/cd_nom/409497"
    }
,
    {
      "name": "Otiorhynchus tenebricosus (Herbst, 1784)",
      "url": "https://inpn.mnhn.fr/espece/cd_nom/242560"
    }
,
    {
      "name": "Curculio clavipes Bonsdorff, 1785",
      "url": "https://inpn.mnhn.fr/espece/cd_nom/409388"
    }
,
    {
      "name": "Curculio fuscipes Olivier, 1807",
      "url": "https://inpn.mnhn.fr/espece/cd_nom/409392"
    }
,
    {
      "name": "Curculio rufipes Sturm, 1791",
      "url": "https://inpn.mnhn.fr/espece/cd_nom/409390"
    }
,
    {
      "name": "Curculio tenebricosus Herbst, 1784",
      "url": "https://inpn.mnhn.fr/espece/cd_nom/803581"
    }
,
    {
      "name": "Otiorhynchus clavipes (Bondsorff, 1785)",
      "url": "https://inpn.mnhn.fr/espece/cd_nom/11810"
    }
,
    {
      "name": "Otiorhynchus erythropus Boheman, 1843",
      "url": "https://inpn.mnhn.fr/espece/cd_nom/409398"
    }
,
    {
      "name": "Otiorhynchus evertsi Uyttenboogaart, 1931",
      "url": "https://inpn.mnhn.fr/espece/cd_nom/409414"
    }
,
    {
      "name": "Otiorhynchus fagi Gyllenhal, 1834",
      "url": "https://inpn.mnhn.fr/espece/cd_nom/409397"
    }
,
    {
      "name": "Otiorhynchus olivieri Abbazzi & Osella, 1992",
      "url": "https://inpn.mnhn.fr/espece/cd_nom/409418"
    }
,
    {
      "name": "Otiorhynchus subglaber Reitter, 1913",
      "url": "https://inpn.mnhn.fr/espece/cd_nom/409410"
    }
,
    {
      "name": "Otiorhynchus substriatus Silbermann, 1833",
      "url": "https://inpn.mnhn.fr/espece/cd_nom/409396"
    }
,
    {
      "name": "Otiorhynchus walloni Smith, 1869",
      "url": "https://inpn.mnhn.fr/espece/cd_nom/409404"
    }
,
    {
      "name": "Otiorhynchus tener Stierlin, 1861",
      "url": "https://inpn.mnhn.fr/espece/cd_nom/13046"
    }
,
    {
      "name": "Otiorhynchus tener bonvouloiri Stierlin, 1866",
      "url": "https://inpn.mnhn.fr/espece/cd_nom/326968"
    }
,
    {
      "name": "Otiorhynchus tener tener Stierlin, 1861",
      "url": "https://inpn.mnhn.fr/espece/cd_nom/252871"
    }
,
    {
      "name": "Otiorhynchus grajus K. Daniel & J. Daniel, 1898",
      "url": "https://inpn.mnhn.fr/espece/cd_nom/798424"
    }
,
    {
      "name": "Otiorhynchus tenuicostis Hustache, 1920",
      "url": "https://inpn.mnhn.fr/espece/cd_nom/12453"
    }
,
    {
      "name": "Otiorrhynchus tenuicostis Hustache, 1920",
      "url": "https://inpn.mnhn.fr/espece/cd_nom/978979"
    }
,
    {
      "name": "Otiorhynchus terricola (Linder, 1863)",
      "url": "https://inpn.mnhn.fr/espece/cd_nom/242575"
    }
,
    {
      "name": "Troglorhynchus terricola Linder, 1863",
      "url": "https://inpn.mnhn.fr/espece/cd_nom/13124"
    }
,
    {
      "name": "Otiorhynchus uncinatus Germar, 1823",
      "url": "https://inpn.mnhn.fr/espece/cd_nom/12439"
    }
,
    {
      "name": "Otiorhynchus setifer Boheman, 1843",
      "url": "https://inpn.mnhn.fr/espece/cd_nom/409467"
    }
,
    {
      "name": "Otiorhynchus varius Boheman, 1842",
      "url": "https://inpn.mnhn.fr/espece/cd_nom/13011"
    }
,
    {
      "name": "Otiorhynchus (Dorymerus) varius ",
      "url": "https://inpn.mnhn.fr/espece/cd_nom/13012"
    }
,
    {
      "name": "Otiorhynchus maritimus Stierlin",
      "url": "https://inpn.mnhn.fr/espece/cd_nom/13014"
    }
,
    {
      "name": "Otiorhynchus maritimus Stierlin, 1883",
      "url": "https://inpn.mnhn.fr/espece/cd_nom/409487"
    }
,
    {
      "name": "Otiorhynchus velutinus Germar, 1823",
      "url": "https://inpn.mnhn.fr/espece/cd_nom/13113"
    }
,
    {
      "name": "Otiorhynchus cerdanensis Jacquet, 1888",
      "url": "https://inpn.mnhn.fr/espece/cd_nom/409582"
    }
,
    {
      "name": "Otiorhynchus cerdeanensis ",
      "url": "https://inpn.mnhn.fr/espece/cd_nom/13120"
    }
,
    {
      "name": "Otiorhynchus desbrochersi Stierlin, 1896",
      "url": "https://inpn.mnhn.fr/espece/cd_nom/409584"
    }
,
    {
      "name": "Otiorhynchus exilis Boheman, 1843",
      "url": "https://inpn.mnhn.fr/espece/cd_nom/409579"
    }
,
    {
      "name": "Otiorhynchus globithorax Boheman, 1843",
      "url": "https://inpn.mnhn.fr/espece/cd_nom/409578"
    }
,
    {
      "name": "Otiorhynchus godeti Gyllenhal, 1834",
      "url": "https://inpn.mnhn.fr/espece/cd_nom/409577"
    }
,
    {
      "name": "Otiorhynchus humilis Germar, 1823",
      "url": "https://inpn.mnhn.fr/espece/cd_nom/409576"
    }
,
    {
      "name": "Otiorhynchus (Arammichnus) velutinus Germar, 1823",
      "url": "https://inpn.mnhn.fr/espece/cd_nom/13114"
    }
,
    {
      "name": "Otiorhynchus lhesgicus Kolenati, 1858",
      "url": "https://inpn.mnhn.fr/espece/cd_nom/409580"
    }
,
    {
      "name": "Otiorhynchus logesi F. Solari, 1940",
      "url": "https://inpn.mnhn.fr/espece/cd_nom/409586"
    }
,
    {
      "name": "Otiorhynchus proreus Reitter, 1889",
      "url": "https://inpn.mnhn.fr/espece/cd_nom/409583"
    }
,
    {
      "name": "Otiorhynchus simplex Stierlin, 1880",
      "url": "https://inpn.mnhn.fr/espece/cd_nom/409581"
    }
,
    {
      "name": "Otiorhynchus vexator Reitter, 1900",
      "url": "https://inpn.mnhn.fr/espece/cd_nom/409585"
    }
,
    {
      "name": "Otiorhynchus venustus Stierlin, 1880",
      "url": "https://inpn.mnhn.fr/espece/cd_nom/242567"
    }
,
    {
      "name": "Otiorhynchus veterator Uyttenboogaart, 1932",
      "url": "https://inpn.mnhn.fr/espece/cd_nom/242571"
    }
,
    {
      "name": "Otiorhynchus impressiventris veterator Uyttenboogaart, 1932",
      "url": "https://inpn.mnhn.fr/espece/cd_nom/837244"
    }
,
    {
      "name": "Otiorhynchus vitellus Gyllenhal, 1834",
      "url": "https://inpn.mnhn.fr/espece/cd_nom/12450"
    }
,
    {
      "name": "Otiorhynchus Germar, 1822",
      "url": ""
    }
,
    {
      "name": "Pendragon Gozis, 1885",
      "url": ""
    }
,
    {
      "name": "Phalantorrhynchus Reitter, 1912",
      "url": ""
    }
,
    {
      "name": "Podoropelmus Reitter, 1912",
      "url": ""
    }
,
    {
      "name": "Postaremus Reitter, 1912",
      "url": ""
    }
,
    {
      "name": "Prilisvanus Reitter, 1912",
      "url": ""
    }
,
    {
      "name": "Proremus Reitter, 1912",
      "url": ""
    }
,
    {
      "name": "Provadilus Reitter, 1912",
      "url": ""
    }
,
    {
      "name": "Rosvalestus Reitter, 1912",
      "url": ""
    }
,
    {
      "name": "Tithonus Germar, 1824",
      "url": ""
    }
,
    {
      "name": "Zadrehus Reitter, 1912",
      "url": ""
    }
,
    {
      "name": "Zustalestus Reitter, 1912",
      "url": ""
    }
,
    {
      "name": "Pseudocratopus Hustache, 1921",
      "url": ""
    }
,
    {
      "name": "Pseudocratopus costulatus Hustache, 1921",
      "url": "https://inpn.mnhn.fr/espece/cd_nom/711208"
    }
,
    {
      "name": "Pseudocratopus minutus Hustache, 1921",
      "url": "https://inpn.mnhn.fr/espece/cd_nom/711209"
    }
,
    {
      "name": "Solariola Flach, 1908",
      "url": ""
    }
,
    {
      "name": "Solariola gestroi (A. Solari & F. Solari, 1903)",
      "url": "https://inpn.mnhn.fr/espece/cd_nom/242550"
    }
,
    {
      "name": "Otiorhynchus gestroi A. Solari & F. Solari, 1903",
      "url": "https://inpn.mnhn.fr/espece/cd_nom/893563"
    }
,
    {
      "name": "Solariola gestroi clermonti (Normand, 1908)",
      "url": "https://inpn.mnhn.fr/espece/cd_nom/252847"
    }
,
    {
      "name": "Troglorrhynchus (Solariella) gestroi clermonti Normand, 1908",
      "url": "https://inpn.mnhn.fr/espece/cd_nom/884887"
    }
,
    {
      "name": "Stomodes Schönherr, 1826",
      "url": ""
    }
,
    {
      "name": "Stomodes gyrosicollis Boheman, 1842",
      "url": "https://inpn.mnhn.fr/espece/cd_nom/242582"
    }
,
    {
      "name": "Stomodes gyrsicollis Boh., 1843",
      "url": "https://inpn.mnhn.fr/espece/cd_nom/13133"
    }

  ]
}
