
{
  "name": "asellariaceae",
  "children": [

    {
      "name": "Asellariaceae Manier ex Manier & Lichtw., 1968",
      "url": ""
    }
,
    {
      "name": "Asellaria R.A.Poiss., 1932",
      "url": ""
    }
,
    {
      "name": "Asellaria caulleryi R.A.Poiss., 1932",
      "url": "https://inpn.mnhn.fr/espece/cd_nom/950985"
    }
,
    {
      "name": "Asellaria gramenei Tuzet & Manier ex Manier, 1968",
      "url": "https://inpn.mnhn.fr/espece/cd_nom/950996"
    }
,
    {
      "name": "Asellaria ligiae Tuzet & Manier ex Manier, 1968",
      "url": "https://inpn.mnhn.fr/espece/cd_nom/950997"
    }
,
    {
      "name": "Orchesellaria Manier ex Manier & Lichtw., 1965",
      "url": ""
    }
,
    {
      "name": "Orchesellaria mauguioi Manier, 1965",
      "url": "https://inpn.mnhn.fr/espece/cd_nom/950999"
    }
,
    {
      "name": "Orchesellaria podurae Manier, 1979",
      "url": "https://inpn.mnhn.fr/espece/cd_nom/1000525"
    }

  ]
}
