
{
  "name": "panopeinae",
  "children": [

    {
      "name": "Panopeinae Ortmann, 1893",
      "url": ""
    }
,
    {
      "name": "Acantholobulus Felder & Martin, 2003",
      "url": ""
    }
,
    {
      "name": "Acantholobulus pacificus (Edmondson, 1931)",
      "url": "https://inpn.mnhn.fr/espece/cd_nom/596849"
    }
,
    {
      "name": "Panopeus pacificus Edmondson, 1931",
      "url": "https://inpn.mnhn.fr/espece/cd_nom/695514"
    }
,
    {
      "name": "Eurypanopeus A. Milne-Edwards, 1880",
      "url": ""
    }
,
    {
      "name": "Eurypanopeus abbreviatus (Stimpson, 1860)",
      "url": "https://inpn.mnhn.fr/espece/cd_nom/649451"
    }
,
    {
      "name": "Panopeus abbreviatus Stimpson, 1860",
      "url": "https://inpn.mnhn.fr/espece/cd_nom/694691"
    }
,
    {
      "name": "Panopeus politus Smith, 1869",
      "url": "https://inpn.mnhn.fr/espece/cd_nom/694692"
    }
,
    {
      "name": "Eurypanopeus depressus (Smith, 1869)",
      "url": "https://inpn.mnhn.fr/espece/cd_nom/649403"
    }
,
    {
      "name": "Panopeus depressus Smith, 1869",
      "url": "https://inpn.mnhn.fr/espece/cd_nom/694296"
    }
,
    {
      "name": "Eurytium Stimpson, 1859",
      "url": ""
    }
,
    {
      "name": "Eurytium limosum (Say, 1818)",
      "url": "https://inpn.mnhn.fr/espece/cd_nom/647698"
    }
,
    {
      "name": "Cancer limosum Say, 1818",
      "url": "https://inpn.mnhn.fr/espece/cd_nom/678567"
    }
,
    {
      "name": "Hexapanopeus Rathbun, 1898",
      "url": ""
    }
,
    {
      "name": "Hexapanopeus angustifrons (Benedict & Rathbun, 1891)",
      "url": "https://inpn.mnhn.fr/espece/cd_nom/649404"
    }
,
    {
      "name": "Panopeus angustifrons Benedict & Rathbun, 1891",
      "url": "https://inpn.mnhn.fr/espece/cd_nom/694297"
    }
,
    {
      "name": "Hexapanopeus caribbaeus (Stimpson, 1871)",
      "url": "https://inpn.mnhn.fr/espece/cd_nom/968766"
    }
,
    {
      "name": "Micropanope caribbaeus Stimpson, 1871",
      "url": "https://inpn.mnhn.fr/espece/cd_nom/968767"
    }
,
    {
      "name": "Tetraxanthus Rathbun, 1898",
      "url": ""
    }
,
    {
      "name": "Tetraxanthus bidentatus (A. Milne-Edwards, 1880)",
      "url": "https://inpn.mnhn.fr/espece/cd_nom/908558"
    }
,
    {
      "name": "Xanthodes bidentatus A. Milne-Edwards, 1880",
      "url": "https://inpn.mnhn.fr/espece/cd_nom/908559"
    }
,
    {
      "name": "Tetraxanthus rathbunae Chace, 1939",
      "url": "https://inpn.mnhn.fr/espece/cd_nom/810805"
    }

  ]
}
