
{
  "name": "comesomatinae",
  "children": [

    {
      "name": "Comesomatinae Filipjev, 1918",
      "url": ""
    }
,
    {
      "name": "Comesoma Bastian, 1865",
      "url": ""
    }
,
    {
      "name": "Comesoma simile Cobb N.A., 1898",
      "url": "https://inpn.mnhn.fr/espece/cd_nom/989917"
    }
,
    {
      "name": "Comesoma vulgare Bastian, 1865",
      "url": "https://inpn.mnhn.fr/espece/cd_nom/385541"
    }
,
    {
      "name": "Comesoma vulgarae Bastian, 1865",
      "url": "https://inpn.mnhn.fr/espece/cd_nom/64965"
    }
,
    {
      "name": "Comesoma vulgaris Bastian, 1865",
      "url": "https://inpn.mnhn.fr/espece/cd_nom/986504"
    }
,
    {
      "name": "Paracomesoma Schuurmans Stekhoven, 1950",
      "url": ""
    }
,
    {
      "name": "Paracomesoma dubium (Filipjev, 1918)",
      "url": "https://inpn.mnhn.fr/espece/cd_nom/986989"
    }
,
    {
      "name": "Comesoma dubium Filipjev, 1918",
      "url": "https://inpn.mnhn.fr/espece/cd_nom/986990"
    }

  ]
}
