
{
  "name": "margarodidae",
  "children": [

    {
      "name": "Margarodidae Guilging, 1829",
      "url": ""
    }
,
    {
      "name": "Dimargarodes Silvestri, 1938",
      "url": ""
    }
,
    {
      "name": "Dimargarodes mediterraneus (Silvestri, 1906)",
      "url": "https://inpn.mnhn.fr/espece/cd_nom/221732"
    }
,
    {
      "name": "Margarodes mediterraneus Silvestri, 1906",
      "url": "https://inpn.mnhn.fr/espece/cd_nom/893302"
    }
,
    {
      "name": "Gueriniella Fernald, 1903",
      "url": ""
    }
,
    {
      "name": "Gueriniella serratulae (Fabricius, 1775)",
      "url": "https://inpn.mnhn.fr/espece/cd_nom/221733"
    }
,
    {
      "name": "Coccus serratulae Fabricius, 1775",
      "url": "https://inpn.mnhn.fr/espece/cd_nom/893309"
    }
,
    {
      "name": "Gueriniella decorata Borchsenius, 1949",
      "url": "https://inpn.mnhn.fr/espece/cd_nom/393444"
    }
,
    {
      "name": "Kuwania Cockerell in Fernald, 1903",
      "url": ""
    }
,
    {
      "name": "Kuwania rubra Goux, 1938",
      "url": "https://inpn.mnhn.fr/espece/cd_nom/221736"
    }
,
    {
      "name": "Marchalina Vayssiere, 1923",
      "url": ""
    }
,
    {
      "name": "Marchalina hellenica (Gennadius, 1883)",
      "url": "https://inpn.mnhn.fr/espece/cd_nom/221737"
    }
,
    {
      "name": "Margarodes Guilding, 1829",
      "url": ""
    }
,
    {
      "name": "Margarodes gallicus (Signoret, 1854)",
      "url": "https://inpn.mnhn.fr/espece/cd_nom/893303"
    }
,
    {
      "name": "Margarodes perrisii (Signoret, 1876)",
      "url": "https://inpn.mnhn.fr/espece/cd_nom/893304"
    }
,
    {
      "name": "Matsucoccus Cockerell, 1909",
      "url": ""
    }
,
    {
      "name": "Matsucoccus feytaudi Ducasse, 1941",
      "url": "https://inpn.mnhn.fr/espece/cd_nom/221738"
    }
,
    {
      "name": "Matsucoccus matsumurae (Kuwana, 1905)",
      "url": "https://inpn.mnhn.fr/espece/cd_nom/221739"
    }
,
    {
      "name": "Kuwania pini Green, 1925",
      "url": "https://inpn.mnhn.fr/espece/cd_nom/393446"
    }
,
    {
      "name": "Matsucoccus insignis Borchsenius, 1955",
      "url": "https://inpn.mnhn.fr/espece/cd_nom/393445"
    }
,
    {
      "name": "Neomargarodes Green, 1914",
      "url": ""
    }
,
    {
      "name": "Neomargarodes europaeus Goidanich, 1969",
      "url": "https://inpn.mnhn.fr/espece/cd_nom/221740"
    }
,
    {
      "name": "Neomargarodes festucae Archangelskaya, 1935",
      "url": "https://inpn.mnhn.fr/espece/cd_nom/221741"
    }
,
    {
      "name": "Palaeococcus Cockerell, 1894",
      "url": ""
    }
,
    {
      "name": "Palaeococcus fuscipennis (Burmeister, 1839)",
      "url": "https://inpn.mnhn.fr/espece/cd_nom/221742"
    }
,
    {
      "name": "Monophlebus fuscipennis Burmeister, 1839",
      "url": "https://inpn.mnhn.fr/espece/cd_nom/893311"
    }
,
    {
      "name": "Porphyrophora Brandt, 1833",
      "url": ""
    }
,
    {
      "name": "Porphyrophora crithmi (Goux, 1938)",
      "url": "https://inpn.mnhn.fr/espece/cd_nom/221743"
    }
,
    {
      "name": "Margarodes crithmi Goux, 1938",
      "url": "https://inpn.mnhn.fr/espece/cd_nom/893305"
    }
,
    {
      "name": "Margarodes madraguensis Goux, 1946",
      "url": "https://inpn.mnhn.fr/espece/cd_nom/393447"
    }
,
    {
      "name": "Porphyrophora madraguensis (Goux, 1946)",
      "url": "https://inpn.mnhn.fr/espece/cd_nom/893306"
    }
,
    {
      "name": "Porphyrophora polonica (Linnaeus, 1758)",
      "url": "https://inpn.mnhn.fr/espece/cd_nom/221744"
    }
,
    {
      "name": "Coccus polonicus Linnaeus, 1758",
      "url": "https://inpn.mnhn.fr/espece/cd_nom/849000"
    }
,
    {
      "name": "Steatococcus ",
      "url": ""
    }
,
    {
      "name": "Steatococcus samaraius Morrison, 1927",
      "url": "https://inpn.mnhn.fr/espece/cd_nom/439650"
    }
,
    {
      "name": "Steingelia Nassonov, 1908",
      "url": ""
    }
,
    {
      "name": "Steingelia gorodetskia Nassonov, 1908",
      "url": "https://inpn.mnhn.fr/espece/cd_nom/221745"
    }
,
    {
      "name": "Xylococcus Low, 1883",
      "url": ""
    }
,
    {
      "name": "Xylococcus filiferus Löw, 1883",
      "url": "https://inpn.mnhn.fr/espece/cd_nom/221746"
    }

  ]
}
