
{
  "name": "molidae",
  "children": [

    {
      "name": "Molidae Bonaparte, 1835",
      "url": ""
    }
,
    {
      "name": "Masturus Gill, 1884",
      "url": ""
    }
,
    {
      "name": "Masturus lanceolatus (Liénard, 1840)",
      "url": "https://inpn.mnhn.fr/espece/cd_nom/70693"
    }
,
    {
      "name": "Masturus lanceolata (Liénard, 1840)",
      "url": "https://inpn.mnhn.fr/espece/cd_nom/559207"
    }
,
    {
      "name": "Mola lanceolata (Liénard, 1840)",
      "url": "https://inpn.mnhn.fr/espece/cd_nom/559210"
    }
,
    {
      "name": "Mola lanceolatus (Liénard, 1840)",
      "url": "https://inpn.mnhn.fr/espece/cd_nom/559211"
    }
,
    {
      "name": "Orthagoriscus lanceolatus Liénard, 1840",
      "url": "https://inpn.mnhn.fr/espece/cd_nom/561092"
    }
,
    {
      "name": "Pseudomola lassarati Cadenat, 1959",
      "url": "https://inpn.mnhn.fr/espece/cd_nom/567479"
    }
,
    {
      "name": "Mola Koelreuter, 1766",
      "url": ""
    }
,
    {
      "name": "Mola alexandrini (Ranzani, 1839)",
      "url": "https://inpn.mnhn.fr/espece/cd_nom/888258"
    }
,
    {
      "name": "Mola mola auct. non (Linnaeus, 1758)",
      "url": "https://inpn.mnhn.fr/espece/cd_nom/888261"
    }
,
    {
      "name": "Mola ramsayi (Giglioli, 1883)",
      "url": "https://inpn.mnhn.fr/espece/cd_nom/651555"
    }
,
    {
      "name": "Orthagoriscus alessandrini Ranzani, 1839",
      "url": "https://inpn.mnhn.fr/espece/cd_nom/888259"
    }
,
    {
      "name": "Orthragoriscus alexandrini Ranzani, 1839",
      "url": "https://inpn.mnhn.fr/espece/cd_nom/564141"
    }
,
    {
      "name": "Orthragoriscus eurypterus Philippi, 1892",
      "url": "https://inpn.mnhn.fr/espece/cd_nom/693038"
    }
,
    {
      "name": "Orthragoriscus ramsayi Giglioli, 1883",
      "url": "https://inpn.mnhn.fr/espece/cd_nom/693039"
    }
,
    {
      "name": "Ozodura alessandrinii (Ranzani, 1839)",
      "url": "https://inpn.mnhn.fr/espece/cd_nom/888260"
    }
,
    {
      "name": "Mola mola (Linnaeus, 1758)",
      "url": "https://inpn.mnhn.fr/espece/cd_nom/70697"
    }
,
    {
      "name": "Aledon capensis Castelnau, 1861",
      "url": "https://inpn.mnhn.fr/espece/cd_nom/564424"
    }
,
    {
      "name": "Aledon storeri Castelnau, 1861",
      "url": "https://inpn.mnhn.fr/espece/cd_nom/564425"
    }
,
    {
      "name": "Cephalus brevis Shaw, 1804",
      "url": "https://inpn.mnhn.fr/espece/cd_nom/562019"
    }
,
    {
      "name": "Cephalus ortagoriscus Risso, 1827",
      "url": "https://inpn.mnhn.fr/espece/cd_nom/562023"
    }
,
    {
      "name": "Cephalus pallasianus Shaw, 1804",
      "url": "https://inpn.mnhn.fr/espece/cd_nom/562024"
    }
,
    {
      "name": "Diodon carinatus Mitchill, 1828",
      "url": "https://inpn.mnhn.fr/espece/cd_nom/559109"
    }
,
    {
      "name": "Diodon mola Pallas, 1770",
      "url": "https://inpn.mnhn.fr/espece/cd_nom/559113"
    }
,
    {
      "name": "Diodon nummularis Walbaum, 1792",
      "url": "https://inpn.mnhn.fr/espece/cd_nom/559117"
    }
,
    {
      "name": "Diplanchias nasus Rafinesque, 1810",
      "url": "https://inpn.mnhn.fr/espece/cd_nom/564716"
    }
,
    {
      "name": "Mola aculeata Koelreuter, 1766",
      "url": "https://inpn.mnhn.fr/espece/cd_nom/546884"
    }
,
    {
      "name": "Mola aspera Nardo, 1827",
      "url": "https://inpn.mnhn.fr/espece/cd_nom/559208"
    }
,
    {
      "name": "Mola hispida Nardo, 1827",
      "url": "https://inpn.mnhn.fr/espece/cd_nom/559209"
    }
,
    {
      "name": "Mola rotunda Cuvier, 1798",
      "url": "https://inpn.mnhn.fr/espece/cd_nom/559213"
    }
,
    {
      "name": "Molacanthus pallasii Swainson, 1839",
      "url": "https://inpn.mnhn.fr/espece/cd_nom/564881"
    }
,
    {
      "name": "Orthagoriscus mola ",
      "url": "https://inpn.mnhn.fr/espece/cd_nom/546885"
    }
,
    {
      "name": "Orthragoriscus analis Ayres, 1859",
      "url": "https://inpn.mnhn.fr/espece/cd_nom/564142"
    }
,
    {
      "name": "Orthragoriscus blochii Ranzani, 1839",
      "url": "https://inpn.mnhn.fr/espece/cd_nom/564144"
    }
,
    {
      "name": "Orthragoriscus elegans Ranzani, 1839",
      "url": "https://inpn.mnhn.fr/espece/cd_nom/564145"
    }
,
    {
      "name": "Orthragoriscus fasciatus Bloch & Schneider, 1801",
      "url": "https://inpn.mnhn.fr/espece/cd_nom/564146"
    }
,
    {
      "name": "Orthragoriscus ghini Ranzani, 1839",
      "url": "https://inpn.mnhn.fr/espece/cd_nom/564147"
    }
,
    {
      "name": "Orthragoriscus hispidus Bloch & Schneider, 1801",
      "url": "https://inpn.mnhn.fr/espece/cd_nom/564148"
    }
,
    {
      "name": "Orthragoriscus lunaris Gronow, 1854",
      "url": "https://inpn.mnhn.fr/espece/cd_nom/564149"
    }
,
    {
      "name": "Orthragoriscus mola (Linnaeus, 1758)",
      "url": "https://inpn.mnhn.fr/espece/cd_nom/564150"
    }
,
    {
      "name": "Orthragoriscus redi Ranzani, 1839",
      "url": "https://inpn.mnhn.fr/espece/cd_nom/564152"
    }
,
    {
      "name": "Orthragoriscus retzii Ranzani, 1839",
      "url": "https://inpn.mnhn.fr/espece/cd_nom/564153"
    }
,
    {
      "name": "Orthragoriscus rondeletti Ranzani, 1839",
      "url": "https://inpn.mnhn.fr/espece/cd_nom/564154"
    }
,
    {
      "name": "Orthragus luna Rafinesque, 1810",
      "url": "https://inpn.mnhn.fr/espece/cd_nom/564157"
    }
,
    {
      "name": "Ozodura orsini Ranzani, 1839",
      "url": "https://inpn.mnhn.fr/espece/cd_nom/565703"
    }
,
    {
      "name": "Pedalion gigas Guilding, 1838",
      "url": "https://inpn.mnhn.fr/espece/cd_nom/566044"
    }
,
    {
      "name": "Tetraodon mola Linnaeus, 1758",
      "url": "https://inpn.mnhn.fr/espece/cd_nom/546886"
    }
,
    {
      "name": "Trematopsis willugbei Ranzani, 1839",
      "url": "https://inpn.mnhn.fr/espece/cd_nom/567514"
    }
,
    {
      "name": "Tympanomium planci Ranzani, 1839",
      "url": "https://inpn.mnhn.fr/espece/cd_nom/563432"
    }
,
    {
      "name": "Ranzania Nardo, 1840",
      "url": ""
    }
,
    {
      "name": "Ranzania laevis (Pennant, 1776)",
      "url": "https://inpn.mnhn.fr/espece/cd_nom/70700"
    }
,
    {
      "name": "Cephalus cocherani Traill, 1832",
      "url": "https://inpn.mnhn.fr/espece/cd_nom/562020"
    }
,
    {
      "name": "Cephalus elongatus Risso, 1827",
      "url": "https://inpn.mnhn.fr/espece/cd_nom/562021"
    }
,
    {
      "name": "Cephalus oblongus Shaw, 1804",
      "url": "https://inpn.mnhn.fr/espece/cd_nom/562022"
    }
,
    {
      "name": "Cephalus varius Shaw, 1804",
      "url": "https://inpn.mnhn.fr/espece/cd_nom/562025"
    }
,
    {
      "name": "Diodon dimidiatus Walbaum, 1792",
      "url": "https://inpn.mnhn.fr/espece/cd_nom/559110"
    }
,
    {
      "name": "Mola planci Nardo, 1827",
      "url": "https://inpn.mnhn.fr/espece/cd_nom/559212"
    }
,
    {
      "name": "Orthragoriscus battarae Ranzani, 1839",
      "url": "https://inpn.mnhn.fr/espece/cd_nom/564143"
    }
,
    {
      "name": "Orthragoriscus oblongus Bloch & Schneider, 1801",
      "url": "https://inpn.mnhn.fr/espece/cd_nom/564151"
    }
,
    {
      "name": "Orthragoriscus solaris Gronow, 1854",
      "url": "https://inpn.mnhn.fr/espece/cd_nom/564155"
    }
,
    {
      "name": "Orthragoriscus truncatus (Retzius, 1785)",
      "url": "https://inpn.mnhn.fr/espece/cd_nom/564156"
    }
,
    {
      "name": "Orthragus oblongus Rafinesque, 1810",
      "url": "https://inpn.mnhn.fr/espece/cd_nom/564158"
    }
,
    {
      "name": "Ostracion boops Richardson, 1845",
      "url": "https://inpn.mnhn.fr/espece/cd_nom/562041"
    }
,
    {
      "name": "Ostracion laevis Pennant, 1776",
      "url": "https://inpn.mnhn.fr/espece/cd_nom/562052"
    }
,
    {
      "name": "Ranzania makua Jenkins, 1895",
      "url": "https://inpn.mnhn.fr/espece/cd_nom/559214"
    }
,
    {
      "name": "Ranzania truncata (Retzius, 1785)",
      "url": "https://inpn.mnhn.fr/espece/cd_nom/70701"
    }
,
    {
      "name": "Ranzania typus Nardo, 1840",
      "url": "https://inpn.mnhn.fr/espece/cd_nom/559215"
    }
,
    {
      "name": "Tetraodon truncatus Retzius, 1785",
      "url": "https://inpn.mnhn.fr/espece/cd_nom/561123"
    }
,
    {
      "name": "Ranzania sagittaria Claparède, 1870",
      "url": "https://inpn.mnhn.fr/espece/cd_nom/987418"
    }

  ]
}
