
{
  "name": "alcidae",
  "children": [

    {
      "name": "Alcidae Leach, 1820",
      "url": ""
    }
,
    {
      "name": "Alca Linnaeus, 1758",
      "url": ""
    }
,
    {
      "name": "Alca torda Linnaeus, 1758",
      "url": "https://inpn.mnhn.fr/espece/cd_nom/3388"
    }
,
    {
      "name": "Alca torda britannica Ticehurst, 1936",
      "url": "https://inpn.mnhn.fr/espece/cd_nom/3390"
    }
,
    {
      "name": "Alle Link, 1806",
      "url": ""
    }
,
    {
      "name": "Alle alle (Linnaeus, 1758)",
      "url": "https://inpn.mnhn.fr/espece/cd_nom/3396"
    }
,
    {
      "name": "Alca alle Linnaeus, 1758",
      "url": "https://inpn.mnhn.fr/espece/cd_nom/3398"
    }
,
    {
      "name": "Plautus alle (Linnaeus, 1758)",
      "url": "https://inpn.mnhn.fr/espece/cd_nom/3399"
    }
,
    {
      "name": "Plotus alle (Linnaeus, 1758)",
      "url": "https://inpn.mnhn.fr/espece/cd_nom/3400"
    }
,
    {
      "name": "Cepphus Pallas, 1769",
      "url": ""
    }
,
    {
      "name": "Cepphus grylle (Linnaeus, 1758)",
      "url": "https://inpn.mnhn.fr/espece/cd_nom/3392"
    }
,
    {
      "name": "Alca grylle Linnaeus, 1758",
      "url": "https://inpn.mnhn.fr/espece/cd_nom/3394"
    }
,
    {
      "name": "Fratercula Brisson, 1760",
      "url": ""
    }
,
    {
      "name": "Fratercula arctica (Linnaeus, 1758)",
      "url": "https://inpn.mnhn.fr/espece/cd_nom/3402"
    }
,
    {
      "name": "Alca arctica Linnaeus, 1758",
      "url": "https://inpn.mnhn.fr/espece/cd_nom/3404"
    }
,
    {
      "name": "Pinguinus Bonnaterre, 1791",
      "url": ""
    }
,
    {
      "name": "Pinguinus impennis (Linnaeus, 1758)",
      "url": "https://inpn.mnhn.fr/espece/cd_nom/199380"
    }
,
    {
      "name": "Alca impennis Linnaeus, 1758",
      "url": "https://inpn.mnhn.fr/espece/cd_nom/433479"
    }
,
    {
      "name": "Uria Brisson, 1760",
      "url": ""
    }
,
    {
      "name": "Uria aalge (Pontoppidan, 1763)",
      "url": "https://inpn.mnhn.fr/espece/cd_nom/3379"
    }
,
    {
      "name": "Colymbus aalge Pontoppidan, 1763",
      "url": "https://inpn.mnhn.fr/espece/cd_nom/3381"
    }
,
    {
      "name": "Uria aalge aalge (Pontoppidan, 1763)",
      "url": "https://inpn.mnhn.fr/espece/cd_nom/3385"
    }
,
    {
      "name": "Uria aalge albionis Witherby, 1923",
      "url": "https://inpn.mnhn.fr/espece/cd_nom/3386"
    }
,
    {
      "name": "Uria troile (Linnaeus, 1766)",
      "url": "https://inpn.mnhn.fr/espece/cd_nom/986525"
    }
,
    {
      "name": "Uria lomvia (Linnaeus, 1758)",
      "url": "https://inpn.mnhn.fr/espece/cd_nom/3382"
    }
,
    {
      "name": "Alca lomvia Linnaeus, 1758",
      "url": "https://inpn.mnhn.fr/espece/cd_nom/3384"
    }

  ]
}
