
{
  "name": "amphisphaeriaceae",
  "children": [

    {
      "name": "Amphisphaeriaceae G.Winter, 1885",
      "url": ""
    }
,
    {
      "name": "Amphisphaerella (Sacc.) Kirschst., 1934",
      "url": ""
    }
,
    {
      "name": "Amphisphaerella dispersella (Nyl.) O.E.Erikss., 1966",
      "url": "https://inpn.mnhn.fr/espece/cd_nom/854202"
    }
,
    {
      "name": "Amphisphaerella amphisphaerioides (Sacc. & Speg.) Kirschst., 1934",
      "url": "https://inpn.mnhn.fr/espece/cd_nom/871746"
    }
,
    {
      "name": "Microthelia haplospora Norman, 1884",
      "url": "https://inpn.mnhn.fr/espece/cd_nom/871750"
    }
,
    {
      "name": "Rosellinia amphisphaerioides Sacc. & Speg., 1878",
      "url": "https://inpn.mnhn.fr/espece/cd_nom/871747"
    }
,
    {
      "name": "Rosellinia corticalis Allesch., 1886",
      "url": "https://inpn.mnhn.fr/espece/cd_nom/871751"
    }
,
    {
      "name": "Rosellinia dispersella (Nyl.) P.Karst., 1873",
      "url": "https://inpn.mnhn.fr/espece/cd_nom/871748"
    }
,
    {
      "name": "Sphaeria dispersella Nyl., 1855",
      "url": "https://inpn.mnhn.fr/espece/cd_nom/871749"
    }
,
    {
      "name": "Amphisphaerella erikssonii Math., 1993",
      "url": "https://inpn.mnhn.fr/espece/cd_nom/854203"
    }
,
    {
      "name": "Amphisphaerella xylostei (Pers.) Rulamort, 1986",
      "url": "https://inpn.mnhn.fr/espece/cd_nom/45369"
    }
,
    {
      "name": "Amphisphaeria xylostei (Pers.) De Not., 1865",
      "url": "https://inpn.mnhn.fr/espece/cd_nom/871752"
    }
,
    {
      "name": "Anthostoma xylostei (Pers.) Sacc., 1874",
      "url": "https://inpn.mnhn.fr/espece/cd_nom/45370"
    }
,
    {
      "name": "Anthostomella xylostei (Pers.) Guyot, 1958",
      "url": "https://inpn.mnhn.fr/espece/cd_nom/871753"
    }
,
    {
      "name": "Sphaeria xylostei Pers., 1794",
      "url": "https://inpn.mnhn.fr/espece/cd_nom/883388"
    }
,
    {
      "name": "Spilobolus xylostei (Pers.) Link, 1833",
      "url": "https://inpn.mnhn.fr/espece/cd_nom/871754"
    }
,
    {
      "name": "Amphisphaeria Ces. & De Not., 1863",
      "url": ""
    }
,
    {
      "name": "Amphisphaeria abiegna Lambotte & Fautrey, 1894",
      "url": "https://inpn.mnhn.fr/espece/cd_nom/854204"
    }
,
    {
      "name": "Amphisphaeria anceps Sacc. & Briard, 1884",
      "url": "https://inpn.mnhn.fr/espece/cd_nom/854205"
    }
,
    {
      "name": "Amphisphaeria brachyspora Kirschst., 1911",
      "url": "https://inpn.mnhn.fr/espece/cd_nom/854206"
    }
,
    {
      "name": "Amphisphaeria bufonia (Berk. & Broome) Ces. & De Not., 1863",
      "url": "https://inpn.mnhn.fr/espece/cd_nom/854207"
    }
,
    {
      "name": "Massaria bufonia (Berk. & Broome) Tul. & C.Tul., 1863",
      "url": "https://inpn.mnhn.fr/espece/cd_nom/871756"
    }
,
    {
      "name": "Massariella bufonia (Berk. & Broome) Speg., 1880",
      "url": "https://inpn.mnhn.fr/espece/cd_nom/871757"
    }
,
    {
      "name": "Phorcys bufonia (Berk. & Broome) Schröt.",
      "url": "https://inpn.mnhn.fr/espece/cd_nom/871758"
    }
,
    {
      "name": "Poikiloderma bufonia (Berk. & Broome) Füisting",
      "url": "https://inpn.mnhn.fr/espece/cd_nom/871759"
    }
,
    {
      "name": "Sphaeria bufonia Berk. & Broome, 1852",
      "url": "https://inpn.mnhn.fr/espece/cd_nom/871760"
    }
,
    {
      "name": "Amphisphaeria cocos Rolland, 1891",
      "url": "https://inpn.mnhn.fr/espece/cd_nom/854181"
    }
,
    {
      "name": "Amphisphaeria congruella P.Karst., 1873",
      "url": "https://inpn.mnhn.fr/espece/cd_nom/854182"
    }
,
    {
      "name": "Didymosphaeria congruella (P.Karst.) You Z.Wang, Aptroot & K.D.Hyde, 2004",
      "url": "https://inpn.mnhn.fr/espece/cd_nom/993721"
    }
,
    {
      "name": "Amphisphaeria culmicola Sacc., 1873",
      "url": "https://inpn.mnhn.fr/espece/cd_nom/45372"
    }
,
    {
      "name": "Amphisphaeria emiliana Fabre, 1879",
      "url": "https://inpn.mnhn.fr/espece/cd_nom/854183"
    }
,
    {
      "name": "Amphisphaeria fautreyi Sacc., 1898",
      "url": "https://inpn.mnhn.fr/espece/cd_nom/854184"
    }
,
    {
      "name": "Amphisphaeria fibricola Sacc., 1881",
      "url": "https://inpn.mnhn.fr/espece/cd_nom/854185"
    }
,
    {
      "name": "Amphisphaeria fungorum Licent, 1920",
      "url": "https://inpn.mnhn.fr/espece/cd_nom/854186"
    }
,
    {
      "name": "Amphisphaeria heteromera Briard & Sacc., 1885",
      "url": "https://inpn.mnhn.fr/espece/cd_nom/854187"
    }
,
    {
      "name": "Amphisphaeria millepunctata (Fuckel) Petr., 1923",
      "url": "https://inpn.mnhn.fr/espece/cd_nom/45373"
    }
,
    {
      "name": "Amphisphaeria subtecta (Auersw.)",
      "url": "https://inpn.mnhn.fr/espece/cd_nom/871683"
    }
,
    {
      "name": "Diaporthe millepunctata Fuckel, 1874",
      "url": "https://inpn.mnhn.fr/espece/cd_nom/976931"
    }
,
    {
      "name": "Didymosphaeria acerina Rehm, 1874",
      "url": "https://inpn.mnhn.fr/espece/cd_nom/871682"
    }
,
    {
      "name": "Amphisphaeria olearum De Not. & Ces., 1863",
      "url": "https://inpn.mnhn.fr/espece/cd_nom/854188"
    }
,
    {
      "name": "Sphaeria olearum De Not., 1853",
      "url": "https://inpn.mnhn.fr/espece/cd_nom/871684"
    }
,
    {
      "name": "Amphisphaeria paedida (Berk. & Broome) Sacc., 1882",
      "url": "https://inpn.mnhn.fr/espece/cd_nom/45375"
    }
,
    {
      "name": "Sphaeria paedida Berk. & Broome, 1873",
      "url": "https://inpn.mnhn.fr/espece/cd_nom/976932"
    }
,
    {
      "name": "Amphisphaeria parva Vouaux, 1909",
      "url": "https://inpn.mnhn.fr/espece/cd_nom/854189"
    }
,
    {
      "name": "Amphisphaeria pseudoumbrina Sacc., 1873",
      "url": "https://inpn.mnhn.fr/espece/cd_nom/854190"
    }
,
    {
      "name": "Amphisphaeria sepulta (Mont.) Sacc., 1882",
      "url": "https://inpn.mnhn.fr/espece/cd_nom/854191"
    }
,
    {
      "name": "Sphaeria sepulta Mont., 1860",
      "url": "https://inpn.mnhn.fr/espece/cd_nom/871685"
    }
,
    {
      "name": "Amphisphaeria striatispora Cand. & Katum., 1986",
      "url": "https://inpn.mnhn.fr/espece/cd_nom/804021"
    }
,
    {
      "name": "Arecophila striatispora (Cand. & Katum.) You Z.Wang & K.D.Hyde, 2004",
      "url": "https://inpn.mnhn.fr/espece/cd_nom/993719"
    }
,
    {
      "name": "Amphisphaeria terricola G.Winter, 1887",
      "url": "https://inpn.mnhn.fr/espece/cd_nom/854192"
    }
,
    {
      "name": "Amphisphaeria thujina (Peck) Sacc., 1882",
      "url": "https://inpn.mnhn.fr/espece/cd_nom/967844"
    }
,
    {
      "name": "Kirschsteiniothelia thujina (Peck) D.Hawksw., 1985",
      "url": "https://inpn.mnhn.fr/espece/cd_nom/967846"
    }
,
    {
      "name": "Sphaeria thujina Peck, 1875",
      "url": "https://inpn.mnhn.fr/espece/cd_nom/967845"
    }
,
    {
      "name": "Amphisphaeria ulmicola (Curr.) Sacc. & Traverso, 1910",
      "url": "https://inpn.mnhn.fr/espece/cd_nom/45376"
    }
,
    {
      "name": "Sphaeria ulmicola Curr., 1859",
      "url": "https://inpn.mnhn.fr/espece/cd_nom/976933"
    }
,
    {
      "name": "Amphisphaeria umbrina (Fr.) De Not., 1863",
      "url": "https://inpn.mnhn.fr/espece/cd_nom/45377"
    }
,
    {
      "name": "Sphaeria umbrina Fr., 1823",
      "url": "https://inpn.mnhn.fr/espece/cd_nom/871686"
    }
,
    {
      "name": "Amphisphaeria vibratilis (Fuckel) E.Müll., 1962",
      "url": "https://inpn.mnhn.fr/espece/cd_nom/45378"
    }
,
    {
      "name": "Massaria vibratilis Fuckel, 1870",
      "url": "https://inpn.mnhn.fr/espece/cd_nom/871687"
    }
,
    {
      "name": "Massariella vibratilis var. mespili Pass., 1888",
      "url": "https://inpn.mnhn.fr/espece/cd_nom/869037"
    }
,
    {
      "name": "Massariella vibratilis (Fuckel) Sacc., 1882",
      "url": "https://inpn.mnhn.fr/espece/cd_nom/45379"
    }
,
    {
      "name": "Amphisphaeria weygandiorum Maire, 1937",
      "url": "https://inpn.mnhn.fr/espece/cd_nom/854193"
    }
,
    {
      "name": "Broomella Sacc., 1883",
      "url": ""
    }
,
    {
      "name": "Broomella acuta Shoemaker & E.Müll., 1963",
      "url": "https://inpn.mnhn.fr/espece/cd_nom/862263"
    }
,
    {
      "name": "Pestalotia truncata Lév., 1846",
      "url": "https://inpn.mnhn.fr/espece/cd_nom/872252"
    }
,
    {
      "name": "Broomella montaniensis (Ellis & Everh.) E.Müll. & S.Ahmad, 1955",
      "url": "https://inpn.mnhn.fr/espece/cd_nom/45869"
    }
,
    {
      "name": "Arthrobotryum pestalozzioides Dearn. & Fairm., 1918",
      "url": "https://inpn.mnhn.fr/espece/cd_nom/977407"
    }
,
    {
      "name": "Lophiostoma montaniense Ellis & Everh., 1888",
      "url": "https://inpn.mnhn.fr/espece/cd_nom/977406"
    }
,
    {
      "name": "Pestalotia pestalozzioides (Dearn. & Fairm.) Shoemaker & E.Müll., 1963",
      "url": "https://inpn.mnhn.fr/espece/cd_nom/872253"
    }
,
    {
      "name": "Pestalotiopsis pestalozzioides (Dearn. & Fairm.) Nag Raj, 1993",
      "url": "https://inpn.mnhn.fr/espece/cd_nom/977408"
    }
,
    {
      "name": "Broomella verrucosa Shoemaker, C.E.Babc. & E.Müll., 1989",
      "url": "https://inpn.mnhn.fr/espece/cd_nom/862264"
    }
,
    {
      "name": "Broomella vitalbae (Berk. & Broome) Sacc., 1883",
      "url": "https://inpn.mnhn.fr/espece/cd_nom/45870"
    }
,
    {
      "name": "Hypocrea vitalbae Berk. & Broome, 1859",
      "url": "https://inpn.mnhn.fr/espece/cd_nom/977409"
    }
,
    {
      "name": "Kessleria xantha (Sacc.) Höhn.",
      "url": "https://inpn.mnhn.fr/espece/cd_nom/872254"
    }
,
    {
      "name": "Pestalotia vitalbae Shoemaker & E.Müll., 1963",
      "url": "https://inpn.mnhn.fr/espece/cd_nom/872255"
    }
,
    {
      "name": "Ceratosporium Schwein., 1832",
      "url": ""
    }
,
    {
      "name": "Ceratosporium strepticeras (Ces.) Sacc.",
      "url": "https://inpn.mnhn.fr/espece/cd_nom/865701"
    }
,
    {
      "name": "Closterosporium strepticeras (Ces.) Sacc.",
      "url": "https://inpn.mnhn.fr/espece/cd_nom/872833"
    }
,
    {
      "name": "Triposporium streptoceras Ces.",
      "url": "https://inpn.mnhn.fr/espece/cd_nom/872834"
    }
,
    {
      "name": "Ceriophora Höhn., 1919",
      "url": ""
    }
,
    {
      "name": "Ceriophora palustris (Sacc.) Höhn., 1919",
      "url": "https://inpn.mnhn.fr/espece/cd_nom/46123"
    }
,
    {
      "name": "Didymosphaeria palustris Sacc., 1882",
      "url": "https://inpn.mnhn.fr/espece/cd_nom/46124"
    }
,
    {
      "name": "Ceriospora Niessl, 1876",
      "url": ""
    }
,
    {
      "name": "Ceriospora dubyi Niessl, 1876",
      "url": "https://inpn.mnhn.fr/espece/cd_nom/854533"
    }
,
    {
      "name": "Sphaerella ceriospora (Duby) Auersw., 1869",
      "url": "https://inpn.mnhn.fr/espece/cd_nom/872887"
    }
,
    {
      "name": "Sphaeria ceriospora Duby, 1855",
      "url": "https://inpn.mnhn.fr/espece/cd_nom/872888"
    }
,
    {
      "name": "Ceriospora patouillardii Letendre ex Pat., 1886",
      "url": "https://inpn.mnhn.fr/espece/cd_nom/854534"
    }
,
    {
      "name": "Ceriospora polygonacearum (Petr.) Piroz. & Morgan-Jones, 1968",
      "url": "https://inpn.mnhn.fr/espece/cd_nom/46127"
    }
,
    {
      "name": "Amphorulopsis polygonacearum Petr., 1959",
      "url": "https://inpn.mnhn.fr/espece/cd_nom/978179"
    }
,
    {
      "name": "Ceriospora xantha Sacc., 1877",
      "url": "https://inpn.mnhn.fr/espece/cd_nom/854535"
    }
,
    {
      "name": "Chitonospora E.Bommer, M.Rousseau & Sacc., 1890",
      "url": ""
    }
,
    {
      "name": "Chitonospora ammophilae E. Bommer, Rousseau & Sacc.",
      "url": "https://inpn.mnhn.fr/espece/cd_nom/865803"
    }
,
    {
      "name": "Clypeophysalospora H.J.Swart, 1981",
      "url": ""
    }
,
    {
      "name": "Clypeophysalospora latitans (Sacc.) H.J.Swart, 1981",
      "url": "https://inpn.mnhn.fr/espece/cd_nom/905419"
    }
,
    {
      "name": "Amerostege latitans (Sacc.) Theiss., 1917",
      "url": "https://inpn.mnhn.fr/espece/cd_nom/906040"
    }
,
    {
      "name": "Physalospora latitans Sacc., 1893",
      "url": "https://inpn.mnhn.fr/espece/cd_nom/906041"
    }
,
    {
      "name": "Discosia Lib., 1837",
      "url": ""
    }
,
    {
      "name": "Discosia aquatica Fautrey, 1893",
      "url": "https://inpn.mnhn.fr/espece/cd_nom/866003"
    }
,
    {
      "name": "Discosia artocreas (Tode) Fr., 1849",
      "url": "https://inpn.mnhn.fr/espece/cd_nom/866004"
    }
,
    {
      "name": "Sphaeria artocreas Tode, 1791",
      "url": "https://inpn.mnhn.fr/espece/cd_nom/874416"
    }
,
    {
      "name": "Discosia arxii Vanev, 1993",
      "url": "https://inpn.mnhn.fr/espece/cd_nom/866005"
    }
,
    {
      "name": "Discosia ignobilis Fautrey, 1890",
      "url": "https://inpn.mnhn.fr/espece/cd_nom/866006"
    }
,
    {
      "name": "Discosia lauricola Nag Raj, 1993",
      "url": "https://inpn.mnhn.fr/espece/cd_nom/866007"
    }
,
    {
      "name": "Discostroma Clem., 1909",
      "url": ""
    }
,
    {
      "name": "Discostroma caninum Brockmann, 1976",
      "url": "https://inpn.mnhn.fr/espece/cd_nom/862480"
    }
,
    {
      "name": "Discostroma corticola (Fuckel) Brockmann, 1976",
      "url": "https://inpn.mnhn.fr/espece/cd_nom/47181"
    }
,
    {
      "name": "Clathridium corticola (Fuckel) Shoemaker & E.Müll.",
      "url": "https://inpn.mnhn.fr/espece/cd_nom/47182"
    }
,
    {
      "name": "Griphosphaeria corticola (Fuckel) Höhn., 1918",
      "url": "https://inpn.mnhn.fr/espece/cd_nom/47183"
    }
,
    {
      "name": "Leptosphaeria corticola (Fuckel) Sacc., 1878",
      "url": "https://inpn.mnhn.fr/espece/cd_nom/874420"
    }
,
    {
      "name": "Metasphaeria corticola (Fuckel) Sacc., 1883",
      "url": "https://inpn.mnhn.fr/espece/cd_nom/874421"
    }
,
    {
      "name": "Metasphaeria leiostega (Ellis) Sacc., 1883",
      "url": "https://inpn.mnhn.fr/espece/cd_nom/874424"
    }
,
    {
      "name": "Seimatosporium lichenicola (Corda) Shoemaker & E.Müll., 1964",
      "url": "https://inpn.mnhn.fr/espece/cd_nom/874423"
    }
,
    {
      "name": "Sphaeria corticola Fuckel, 1870",
      "url": "https://inpn.mnhn.fr/espece/cd_nom/874422"
    }
,
    {
      "name": "Sphaeria leiostega Ellis, 1881",
      "url": "https://inpn.mnhn.fr/espece/cd_nom/874425"
    }
,
    {
      "name": "Discostroma hyperborea (P.Karst.) O.E.Erikss.",
      "url": "https://inpn.mnhn.fr/espece/cd_nom/862481"
    }
,
    {
      "name": "Didymella hyperborea Sacc., 1882",
      "url": "https://inpn.mnhn.fr/espece/cd_nom/874426"
    }
,
    {
      "name": "Griphosphaeria hyperborea (Sacc.) L.Holm, 1975",
      "url": "https://inpn.mnhn.fr/espece/cd_nom/874427"
    }
,
    {
      "name": "Leiosphaerella hyperborea (Sacc.) E.Müll., 1962",
      "url": "https://inpn.mnhn.fr/espece/cd_nom/876976"
    }
,
    {
      "name": "Paradidymella hyperborea (Sacc.) Petr., 1927",
      "url": "https://inpn.mnhn.fr/espece/cd_nom/876977"
    }
,
    {
      "name": "Sphaeria hyperborea P.Karst., 1872",
      "url": "https://inpn.mnhn.fr/espece/cd_nom/876978"
    }
,
    {
      "name": "Discostroma massarina (Sacc.) Arx, 1974",
      "url": "https://inpn.mnhn.fr/espece/cd_nom/862566"
    }
,
    {
      "name": "Clethridium massarina (Sacc.) Berl., 1899",
      "url": "https://inpn.mnhn.fr/espece/cd_nom/876979"
    }
,
    {
      "name": "Metasphaeria massarina Sacc., 1884",
      "url": "https://inpn.mnhn.fr/espece/cd_nom/876980"
    }
,
    {
      "name": "Discostroma polymorphum Brockmann, 1976",
      "url": "https://inpn.mnhn.fr/espece/cd_nom/862567"
    }
,
    {
      "name": "Griphosphaeria polymorpha (Brockmann) Lar.N.Vassiljeva, 1998",
      "url": "https://inpn.mnhn.fr/espece/cd_nom/876981"
    }
,
    {
      "name": "Discostroma propendulum (P.Karst.) Brockmann, 1976",
      "url": "https://inpn.mnhn.fr/espece/cd_nom/862568"
    }
,
    {
      "name": "Clathridium propendulum (P.Karst.) B. Erikss.",
      "url": "https://inpn.mnhn.fr/espece/cd_nom/876982"
    }
,
    {
      "name": "Sphaeria propendula P.Karst., 1873",
      "url": "https://inpn.mnhn.fr/espece/cd_nom/876983"
    }
,
    {
      "name": "Discostroma rosae Brockmann, 1976",
      "url": "https://inpn.mnhn.fr/espece/cd_nom/862569"
    }
,
    {
      "name": "Discostroma rubicola (Ellis & Everh.) M.E.Barr, 1993",
      "url": "https://inpn.mnhn.fr/espece/cd_nom/862570"
    }
,
    {
      "name": "Coleroa rubicola (Ellis & Everh.) E.Müll., 1962",
      "url": "https://inpn.mnhn.fr/espece/cd_nom/876984"
    }
,
    {
      "name": "Metasphaeria rubicola Ellis & Everh., 1897",
      "url": "https://inpn.mnhn.fr/espece/cd_nom/883399"
    }
,
    {
      "name": "Discostroma sanguineae Brockmann, 1976",
      "url": "https://inpn.mnhn.fr/espece/cd_nom/862571"
    }
,
    {
      "name": "Griphosphaeria sanguineae (Brockmann) Lar.N.Vassiljeva, 1998",
      "url": "https://inpn.mnhn.fr/espece/cd_nom/876985"
    }
,
    {
      "name": "Discostroma strobiligenum (E.Müll. & Loeffler) Brockmann, 1976",
      "url": "https://inpn.mnhn.fr/espece/cd_nom/47184"
    }
,
    {
      "name": "Clethridium strobiligenum E.Müll. & Loeffler, 1958",
      "url": "https://inpn.mnhn.fr/espece/cd_nom/876986"
    }
,
    {
      "name": "Discostroma succinea (Roberge) M.E. Barr",
      "url": "https://inpn.mnhn.fr/espece/cd_nom/862572"
    }
,
    {
      "name": "Amphisphaeria succinea (Roberge ex Desm.) J.C.Krug, 1978",
      "url": "https://inpn.mnhn.fr/espece/cd_nom/876987"
    }
,
    {
      "name": "Charonectria succinea (Roberge ex Desm.) Sacc., 1883",
      "url": "https://inpn.mnhn.fr/espece/cd_nom/876988"
    }
,
    {
      "name": "Leiosphaerella succinea (Roberge ex Desm.) E.Müll., 1962",
      "url": "https://inpn.mnhn.fr/espece/cd_nom/876989"
    }
,
    {
      "name": "Paradidymella succinea (Roberge ex Desm.) Petr., 1927",
      "url": "https://inpn.mnhn.fr/espece/cd_nom/876990"
    }
,
    {
      "name": "Sphaeria succinea Roberge ex Desm., 1848",
      "url": "https://inpn.mnhn.fr/espece/cd_nom/876991"
    }
,
    {
      "name": "Dyrithium M.E.Barr, 1994",
      "url": ""
    }
,
    {
      "name": "Dyrithium lividum (Pers.) M.E.Barr, 1994",
      "url": "https://inpn.mnhn.fr/espece/cd_nom/866261"
    }
,
    {
      "name": "Mycothyridium lividum (Pers.) Petr., 1962",
      "url": "https://inpn.mnhn.fr/espece/cd_nom/877323"
    }
,
    {
      "name": "Sphaeria livida Pers., 1801",
      "url": "https://inpn.mnhn.fr/espece/cd_nom/877324"
    }
,
    {
      "name": "Thyridium lividum (Pers.) Sacc., 1877",
      "url": "https://inpn.mnhn.fr/espece/cd_nom/877325"
    }
,
    {
      "name": "Frondispora K.D.Hyde, 1993",
      "url": ""
    }
,
    {
      "name": "Frondispora bicalcarata (Ces.) K.D.Hyde, 1993",
      "url": "https://inpn.mnhn.fr/espece/cd_nom/968466"
    }
,
    {
      "name": "Ceriospora bicalcarata (Ces.) Sacc., 1883",
      "url": "https://inpn.mnhn.fr/espece/cd_nom/968464"
    }
,
    {
      "name": "Sphaerella bicalcarata Ces., 1872",
      "url": "https://inpn.mnhn.fr/espece/cd_nom/968465"
    }
,
    {
      "name": "Immersidiscosia Kaz.Tanaka, Okane & Hosoya, 2011",
      "url": ""
    }
,
    {
      "name": "Immersidiscosia eucalypti (Pat.) Kaz.Tanaka, Okane & Hosoya, 2011",
      "url": "https://inpn.mnhn.fr/espece/cd_nom/905449"
    }
,
    {
      "name": "Cryptostictis eucalypti Pat., 1897",
      "url": "https://inpn.mnhn.fr/espece/cd_nom/906057"
    }
,
    {
      "name": "Iodosphaeria Samuels, E.Müll. & Petrini, 1987",
      "url": ""
    }
,
    {
      "name": "Iodosphaeria phyllophila (Mouton) Samuels, E.Müll. & Petrini, 1987",
      "url": "https://inpn.mnhn.fr/espece/cd_nom/804026"
    }
,
    {
      "name": "Lasiosphaeria phyllophila Mouton, 1900",
      "url": "https://inpn.mnhn.fr/espece/cd_nom/874522"
    }
,
    {
      "name": "Iodosphaeria tarda (Fuckel) M.E.Barr, 1996",
      "url": "https://inpn.mnhn.fr/espece/cd_nom/855077"
    }
,
    {
      "name": "Sphaeria tarda Fuckel, 1867",
      "url": "https://inpn.mnhn.fr/espece/cd_nom/874523"
    }
,
    {
      "name": "Trichosphaeria tarda (Fuckel) Fuckel, 1870",
      "url": "https://inpn.mnhn.fr/espece/cd_nom/874524"
    }
,
    {
      "name": "Lepteutypa hederae (Fuckel) Rappaz, 1995",
      "url": "https://inpn.mnhn.fr/espece/cd_nom/870926"
    }
,
    {
      "name": "Amphisphaeria hederae Fuckel, 1871",
      "url": "https://inpn.mnhn.fr/espece/cd_nom/979900"
    }
,
    {
      "name": "Lepteutypa sambuci Jaklitsch & Voglmayr, 2016",
      "url": "https://inpn.mnhn.fr/espece/cd_nom/905115"
    }
,
    {
      "name": "Monochaetia (Sacc.) Allesch., 1902",
      "url": ""
    }
,
    {
      "name": "Monochaetia monochaeta (Desm.) Allesch., 1902",
      "url": "https://inpn.mnhn.fr/espece/cd_nom/866536"
    }
,
    {
      "name": "Pestalotia monochaeta Desm., 1848",
      "url": "https://inpn.mnhn.fr/espece/cd_nom/980523"
    }
,
    {
      "name": "Monochaetia muscicola Nicot-Toul., 1947",
      "url": "https://inpn.mnhn.fr/espece/cd_nom/866556"
    }
,
    {
      "name": "Amphichaeta muscicola (J. Nicot) J. Nicot",
      "url": "https://inpn.mnhn.fr/espece/cd_nom/879434"
    }
,
    {
      "name": "Discosia muscicola Nicot-Toul. ex M. Morelet",
      "url": "https://inpn.mnhn.fr/espece/cd_nom/879435"
    }
,
    {
      "name": "Monographella Petr., 1924",
      "url": ""
    }
,
    {
      "name": "Monographella abscondita Döbbeler & Poelt, 1978",
      "url": "https://inpn.mnhn.fr/espece/cd_nom/866557"
    }
,
    {
      "name": "Monographella nivalis (Schaffnit) E.Müll., 1977",
      "url": "https://inpn.mnhn.fr/espece/cd_nom/866559"
    }
,
    {
      "name": "Calonectria nivalis Schaffnit, 1913",
      "url": "https://inpn.mnhn.fr/espece/cd_nom/879444"
    }
,
    {
      "name": "Fusarium nivale (Fr.) Ces.",
      "url": "https://inpn.mnhn.fr/espece/cd_nom/879442"
    }
,
    {
      "name": "Gerlachia nivalis (Fr.) W. Gams & E. Müller",
      "url": "https://inpn.mnhn.fr/espece/cd_nom/879443"
    }
,
    {
      "name": "Griphosphaeria nivalis (Schaffnit) E.Müll. & Arx, 1955",
      "url": "https://inpn.mnhn.fr/espece/cd_nom/879445"
    }
,
    {
      "name": "Micronectriella nivalis (Schaffnit) C.Booth, 1971",
      "url": "https://inpn.mnhn.fr/espece/cd_nom/879446"
    }
,
    {
      "name": "Nectria graminicola Niessl [nom. illeg.]",
      "url": "https://inpn.mnhn.fr/espece/cd_nom/883475"
    }
,
    {
      "name": "Sphaerulina divergens Rehm, 1913",
      "url": "https://inpn.mnhn.fr/espece/cd_nom/879447"
    }
,
    {
      "name": "Neopestalotiopsis Maharachch., K.D.Hyde & Crous, 2014",
      "url": ""
    }
,
    {
      "name": "Neopestalotiopsis magna (Maharachch. & K.D.Hyde) Maharachch., K.D.Hyde & Crous, 2014",
      "url": "https://inpn.mnhn.fr/espece/cd_nom/905123"
    }
,
    {
      "name": "Pestalotiopsis magna Maharachch. & K.D.Hyde, 2014",
      "url": "https://inpn.mnhn.fr/espece/cd_nom/907151"
    }
,
    {
      "name": "Pestalotia capiomonti Bainier & Sartory, 1912",
      "url": "https://inpn.mnhn.fr/espece/cd_nom/856684"
    }
,
    {
      "name": "Pestalotia clusiae Griffon & Maubl., 1909",
      "url": "https://inpn.mnhn.fr/espece/cd_nom/856685"
    }
,
    {
      "name": "Pestalotia guepinii Desm., 1840",
      "url": "https://inpn.mnhn.fr/espece/cd_nom/796744"
    }
,
    {
      "name": "Pestalotia olivacea Guba, 1961",
      "url": "https://inpn.mnhn.fr/espece/cd_nom/856686"
    }
,
    {
      "name": "Pestalotia paeoniae Maubl., 1905",
      "url": "https://inpn.mnhn.fr/espece/cd_nom/856687"
    }
,
    {
      "name": "Monochaetia paeoniae (Maubl.) Sacc. & D.Sacc., 1906",
      "url": "https://inpn.mnhn.fr/espece/cd_nom/879633"
    }
,
    {
      "name": "Robillarda Sacc., 1880",
      "url": ""
    }
,
    {
      "name": "Robillarda vitis Prill. & Delacr., 1890",
      "url": "https://inpn.mnhn.fr/espece/cd_nom/866839"
    }
,
    {
      "name": "Sarcostroma Cooke, 1871",
      "url": ""
    }
,
    {
      "name": "Sarcostroma longiappendiculatum F.Liu, L.Cai & Crous, 2018",
      "url": "https://inpn.mnhn.fr/espece/cd_nom/997328"
    }
,
    {
      "name": "Seimatosporium Corda, 1837",
      "url": ""
    }
,
    {
      "name": "Allelochaeta Petr., 1955",
      "url": ""
    }
,
    {
      "name": "Basipilus Subram., 1961",
      "url": ""
    }
,
    {
      "name": "Vermisporium H.J.Swart & M.A.Will., 1983",
      "url": ""
    }
,
    {
      "name": "Seimatosporium alneum Nag Raj, 1986",
      "url": "https://inpn.mnhn.fr/espece/cd_nom/438136"
    }
,
    {
      "name": "Seimatosporium caninum (Brunaud) B.Sutton, 1975",
      "url": "https://inpn.mnhn.fr/espece/cd_nom/994993"
    }
,
    {
      "name": "Hendersonia canina Brunaud, 1897",
      "url": "https://inpn.mnhn.fr/espece/cd_nom/868890"
    }
,
    {
      "name": "Seimatosporium hypericinum (Ces.) B.Sutton, 1975",
      "url": "https://inpn.mnhn.fr/espece/cd_nom/905596"
    }
,
    {
      "name": "Diploceras hypericinum (Ces.) Died., 1915",
      "url": "https://inpn.mnhn.fr/espece/cd_nom/874857"
    }
,
    {
      "name": "Pestalotia hypericina Ces., 1855",
      "url": "https://inpn.mnhn.fr/espece/cd_nom/907073"
    }
,
    {
      "name": "Seimatosporium ribis-alpini (Fautrey) Shoemaker & E.Müll., 1964",
      "url": "https://inpn.mnhn.fr/espece/cd_nom/857377"
    }
,
    {
      "name": "Seimatosporium rosarum (Henn.) B.Sutton, 1975",
      "url": "https://inpn.mnhn.fr/espece/cd_nom/857378"
    }
,
    {
      "name": "Coryneum rosarum Henn., 1904",
      "url": "https://inpn.mnhn.fr/espece/cd_nom/983409"
    }
,
    {
      "name": "Sporocadus rosarum (Henn.) F.Liu, L.Cai & Crous, 2018",
      "url": "https://inpn.mnhn.fr/espece/cd_nom/983407"
    }
,
    {
      "name": "Seimatosporium tostum (Berk. & Broome) Rossman & W.C.Allen, 2016",
      "url": "https://inpn.mnhn.fr/espece/cd_nom/994485"
    }
,
    {
      "name": "Allelochaeta kriegeriana (Bres.) Crous, 2018",
      "url": "https://inpn.mnhn.fr/espece/cd_nom/994490"
    }
,
    {
      "name": "Clathridium tostum (Berk. & Broome) E. Müller & Shoemaker",
      "url": "https://inpn.mnhn.fr/espece/cd_nom/876994"
    }
,
    {
      "name": "Didymella fuckeliana (Sacc.) Sacc.",
      "url": "https://inpn.mnhn.fr/espece/cd_nom/876992"
    }
,
    {
      "name": "Didymella tosta (Berk. & Broome) Sacc., 1882",
      "url": "https://inpn.mnhn.fr/espece/cd_nom/876995"
    }
,
    {
      "name": "Didymosphaeria fuckeliana Pass. ex Sacc., 1878",
      "url": "https://inpn.mnhn.fr/espece/cd_nom/876993"
    }
,
    {
      "name": "Discosia passerinii Sacc., 1884",
      "url": "https://inpn.mnhn.fr/espece/cd_nom/994491"
    }
,
    {
      "name": "Discostroma tostum (Berk. & Broome) Brockmann, 1976",
      "url": "https://inpn.mnhn.fr/espece/cd_nom/47185"
    }
,
    {
      "name": "Leiosphaerella tosta (Berk. & Broome) E.Müll., 1962",
      "url": "https://inpn.mnhn.fr/espece/cd_nom/876996"
    }
,
    {
      "name": "Paradidymella tosta (Berk. & Broome) Petr., 1927",
      "url": "https://inpn.mnhn.fr/espece/cd_nom/876997"
    }
,
    {
      "name": "Pestalotia kriegeriana Bres., 1894",
      "url": "https://inpn.mnhn.fr/espece/cd_nom/994488"
    }
,
    {
      "name": "Seimatosporium kriegerianum (Bres.) Morgan-Jones & B.Sutton, 1964",
      "url": "https://inpn.mnhn.fr/espece/cd_nom/876998"
    }
,
    {
      "name": "Seimatosporium passerinii (Sacc.) Brockmann, 1976",
      "url": "https://inpn.mnhn.fr/espece/cd_nom/876999"
    }
,
    {
      "name": "Sphaeria tosta Berk. & Broome, 1852",
      "url": "https://inpn.mnhn.fr/espece/cd_nom/883400"
    }
,
    {
      "name": "Sphaeria tritorulosa Plowr., 1878",
      "url": "https://inpn.mnhn.fr/espece/cd_nom/994487"
    }
,
    {
      "name": "Seiridium Nees, 1816",
      "url": ""
    }
,
    {
      "name": "Adea Petr., 1928",
      "url": ""
    }
,
    {
      "name": "Blogiascospora Shoemaker, E.Müll. & Morgan-Jones, 1966",
      "url": ""
    }
,
    {
      "name": "Lepteutypa Petr., 1923",
      "url": ""
    }
,
    {
      "name": "Pestalotia De Not., 1841",
      "url": ""
    }
,
    {
      "name": "Seiridium cardinale (W.W.Wagener) B.Sutton & I.A.S.Gibson, 1972",
      "url": "https://inpn.mnhn.fr/espece/cd_nom/905597"
    }
,
    {
      "name": "Coryneum cardinale W.W.Wagener, 1939",
      "url": "https://inpn.mnhn.fr/espece/cd_nom/906083"
    }
,
    {
      "name": "Seiridium intermedium (Sacc.) B.Sutton, 1975",
      "url": "https://inpn.mnhn.fr/espece/cd_nom/866803"
    }
,
    {
      "name": "Coryneum intermedium Sacc., 1877",
      "url": "https://inpn.mnhn.fr/espece/cd_nom/983410"
    }
,
    {
      "name": "Seiridium marginatum Nees, 1816",
      "url": "https://inpn.mnhn.fr/espece/cd_nom/866804"
    }
,
    {
      "name": "Seynesia Sacc., 1883",
      "url": ""
    }
,
    {
      "name": "Seynesia erumpens (Berk. & M.A.Curtis) Petr., 1927",
      "url": "https://inpn.mnhn.fr/espece/cd_nom/804028"
    }
,
    {
      "name": "Micropeltis erumpens Berk. & M.A.Curtis, 1868",
      "url": "https://inpn.mnhn.fr/espece/cd_nom/908048"
    }
,
    {
      "name": "Synnemapestaloides T.Handa & Y.Harada, 2004",
      "url": ""
    }
,
    {
      "name": "Synnemapestaloides juniperi F.Liu, L.Cai & Crous, 2018",
      "url": "https://inpn.mnhn.fr/espece/cd_nom/997284"
    }
,
    {
      "name": "Xylochora Arx & E.Müll., 1954",
      "url": ""
    }
,
    {
      "name": "Xylochora nigropunctata (Romell) Arx & E.Müll., 1954",
      "url": "https://inpn.mnhn.fr/espece/cd_nom/866681"
    }
,
    {
      "name": "Physalospora nigropunctata Romell, 1889",
      "url": "https://inpn.mnhn.fr/espece/cd_nom/881328"
    }
,
    {
      "name": "Zetiasplozna Nag Raj, 1993",
      "url": ""
    }
,
    {
      "name": "Zetiasplozna acaciae Crous, 2014",
      "url": "https://inpn.mnhn.fr/espece/cd_nom/905189"
    }

  ]
}
