
{
  "name": "hoplichthyidae",
  "children": [

    {
      "name": "Hoplichthyidae Kaup, 1873",
      "url": ""
    }
,
    {
      "name": "Hoplichthys Cuvier, 1829",
      "url": ""
    }
,
    {
      "name": "Hoplichthys citrinus Gilbert, 1905",
      "url": "https://inpn.mnhn.fr/espece/cd_nom/533490"
    }
,
    {
      "name": "Hoplichthys filamentosus Matsubara & Ochiai, 1950",
      "url": "https://inpn.mnhn.fr/espece/cd_nom/891111"
    }
,
    {
      "name": "Hoplichthys gilberti Jordan & Richardson, 1908",
      "url": "https://inpn.mnhn.fr/espece/cd_nom/533491"
    }
,
    {
      "name": "Hoplichthys regani Jordan, 1908",
      "url": "https://inpn.mnhn.fr/espece/cd_nom/791117"
    }

  ]
}
