
{
  "name": "echinodictyinae",
  "children": [

    {
      "name": "Echinodictyinae Hooper, 2002",
      "url": ""
    }
,
    {
      "name": "Echinodictyum Ridley, 1881",
      "url": ""
    }
,
    {
      "name": "Echinodictyum asperum Ridley & Dendy, 1886",
      "url": "https://inpn.mnhn.fr/espece/cd_nom/674714"
    }
,
    {
      "name": "Echinodictyum mesenterinum (Lamarck, 1814)",
      "url": "https://inpn.mnhn.fr/espece/cd_nom/991476"
    }
,
    {
      "name": "Spongia mesenterina Lamarck, 1814",
      "url": "https://inpn.mnhn.fr/espece/cd_nom/991469"
    }

  ]
}
